Workbook
Name L_REM_GERAL: PARAMETROS!$B$5
Name L_REM_PFMEI: PARAMETROS!$B$6
Name L_FORNECEDOR: PARAMETROS!$B$7
Name L_ADM: PARAMETROS!$B$8
Name L_ACESS: PARAMETROS!$B$9
Name L_DIVULG: PARAMETROS!$B$10
Name L_CAPT_PCT: PARAMETROS!$B$11
Name L_CAPT_TETO: PARAMETROS!$B$12
Name L_CACHE_SOLO: PARAMETROS!$B$13
Name L_CACHE_GRUPO: PARAMETROS!$B$14
Name L_CACHE_MUSICO: PARAMETROS!$B$15
Name L_CACHE_MAESTRO: PARAMETROS!$B$16
Name L_CACHE_PALESTRA: PARAMETROS!$B$17
Name L_INICIANTE: PARAMETROS!$B$18
Name L_DIST_PATROC: PARAMETROS!$B$19
Name L_DIST_PROPON: PARAMETROS!$B$20
Name L_DIST_SOCIAL: PARAMETROS!$B$21
Name L_DIST_POPULAR: PARAMETROS!$B$22
Name L_PRECO_POPULAR: PARAMETROS!$B$23
Name L_TICKET_MEDIO: PARAMETROS!$B$24
Name L_PF_QTD: PARAMETROS!$B$25
Name L_PF_TETO: PARAMETROS!$B$26
Name L_MEI_QTD: PARAMETROS!$B$27
Name L_MEI_TETO: PARAMETROS!$B$28
Name L_PJ_QTD: PARAMETROS!$B$29
Name L_PJ_TETO: PARAMETROS!$B$30
Name MARGEM: PARAMETROS!$B$31
Name LISTA_CATEGORIAS: PARAMETROS!$I$5:$I$17
Name TAB_CATEGORIAS: PARAMETROS!$I$5:$J$17
Name LISTA_ETAPAS: PARAMETROS!$L$5:$L$12
Name VALOR_INCENTIVO: 'ORÇAMENTO'!$C$3
Name VALOR_OUTRAS: 'ORÇAMENTO'!$C$4
Name VALOR_TOTAL: 'ORÇAMENTO'!$C$5
Name DIST_STATUS1: DISTRIBUICAO!$G$7
Name VALOR_PROJETO: 'RADAR DE LIMITES'!$B$9
Name VALOR_CAPTADO: 'RADAR DE LIMITES'!$B$12
Name TIPO_PROP: 'RADAR DE LIMITES'!$B$5

Sheet COMECE AQUI
A1: ROUANET 31/10 — Planilhas de Execução
A2: Kit de organização e conferência. Não garante aprovação nem captação. Base normativa: Lei 8.313/1991, Decreto 11.453/2023 e IN MinC nº 29/2026 (verificação: 25/09/2026). Sempre confira a norma vigente no site do Ministério da Cultura.
A4: ORDEM | B4: ABA | C4: O QUE FAZER | D4: TEMPO
A5: 1 | B5: PARAMETROS | C5: Confira se os limites estão iguais aos da norma vigente. Só altere se a norma mudar (células amarelas). | D5: 5 min
A6: 2 | B6: MAPA DO PROJETO | C6: Preencha a ideia do projeto campo a campo. É o texto-base do Salic. | D6: 2–3 h
A7: 3 | B7: ORÇAMENTO | C7: Lance cada despesa. Preencha também as colunas cinza de conferência (categoria, vínculo, preço, dupla cobertura). | D7: 2–4 h
A8: 4 | B8: CRONOGRAMA | C8: Lance as atividades com início e fim. O gráfico de barras e os alertas aparecem sozinhos. | D8: 1 h
A9: 5 | B9: DISTRIBUICAO | C9: Informe quantos ingressos/produtos existem e como serão distribuídos. | D9: 30 min
A10: 6 | B10: RADAR DE LIMITES | C10: Informe tipo de proponente e cenário de captação. Leia os status 🟢🟡🔴. | D10: 20 min
A11: 7 | B11: MATRIZ CONSISTENCIA | C11: Ligue cada objetivo a meta, produto, despesa, atividade e público. | D11: 40 min
A12: 8 | B12: CHECKLIST DOCUMENTOS | C12: Marque o que se aplica e o que você já tem. | D12: 30 min
A13: 9 | B13: CHECKLIST SALIC | C13: Use ao preencher o sistema, etapa por etapa. | D13: durante o Salic
A14: 10 | B14: CHECKLIST FINAL | C14: 50 verificações antes de clicar em enviar. Meta: zero 'NÃO'. | D14: 40 min
A15: 11 | B15: CONTROLE NORMATIVO | C15: Registre a data em que você conferiu a norma oficial. | D15: 5 min
A17: LEGENDA DE CORES
B18: Amarelo claro = você preenche
B19: Cinza = fórmula automática (não apague)
B20: 🟢 = dentro do limite / conferido / coerente
B21: 🟡 = verificar / revisar (perto do limite ou informação faltando)
B22: 🔴 = acima do limite / risco alto / inconsistente
A24: REGRA DE OURO | B24: SE NÃO CONSIGO EXPLICAR POR QUE ESSA DESPESA EXISTE, NÃO COLOQUE A DESPESA.
A26: IMPORTANTE: as calculadoras são ferramentas de CONFERÊNCIA prévia. O Salic aplica as fórmulas oficiais e o Ministério da Cultura faz a análise técnica. 🟢 na planilha não significa aprovação — significa apenas que o número informado está dentro do limite configurado na aba PARAMETROS.

Sheet PARAMETROS
A1: PARÂMETROS NORMATIVOS (IN MinC nº 29/2026)
A2: Células amarelas = limites usados por todas as calculadoras. Confira cada linha no texto oficial antes de usar. Se a norma mudar, altere aqui.
A4: Regra | B4: Limite | C4: Base de cálculo | D4: Quem está sujeito | E4: Exceções / observações | F4: Fonte (confira no texto oficial) | G4: Status da verificação | I4: Categorias de limite (listas) | J4: Limite unitário | L4: Etapas
A5: Remuneração do proponente – regra geral | B5: 0.2 | C5: VALOR CAPTADO | D5: Proponente que presta serviço ao projeto previsto no orçamento analítico. Pagamentos a cônjuge, companheiro(a), empresa coligada ou com sócio em comum SOMAM neste limite. | E5: Não se aplica a grupos artísticos familiares, corpos artísticos estáveis e grupos/coletivos culturais que atuem na execução do projeto (ver texto oficial). PF e MEI têm limite próprio (linha abaixo). | F5: IN MinC 29/2026 – dispositivo sobre remuneração do proponente | G5: ☐ conferido no texto oficial em ___/___/2026 | I5: Produção / atividade-fim | L5: Pré-produção
A6: Remuneração do proponente – pessoa física ou MEI | B6: 0.3 | C6: VALOR CAPTADO | D6: Proponente pessoa física ou microempreendedor individual. | E6: Continua exigindo serviço efetivo previsto no orçamento. | F6: IN MinC 29/2026 – mesmo dispositivo | G6: ☐ conferido no texto oficial em ___/___/2026 | I6: Cachê – artista solo | J6: =L_CACHE_SOLO | L6: Produção / Execução
A7: Pagamento a um mesmo fornecedor | B7: 0.2 | C7: VALOR CAPTADO | D7: Qualquer fornecedor pago com recurso incentivado. | E7: Há exceções previstas (ex.: intervenções de conservação e restauro de bens culturais). Confira a lista completa no texto oficial. | F7: IN MinC 29/2026 – dispositivo sobre limite por fornecedor | G7: ☐ conferido no texto oficial em ___/___/2026 | I7: Cachê – grupo ou coletivo | J7: =L_CACHE_GRUPO | L7: Pós-produção
A8: Custos de administração | B8: 0.15 | C8: VALOR DO PROJETO | D8: Todos os projetos. | E8: Pagos proporcionalmente às parcelas captadas. 2026: regularização documental de bens de patrimônio passou a ser admitida como custo administrativo; caiu a regra de não concentrar mais de 50% em uma única despesa administrativa. | F8: IN MinC 29/2026 – custos vinculados | G8: ☐ conferido no texto oficial em ___/___/2026 | I8: Cachê – músico de orquestra | J8: =L_CACHE_MUSICO | L8: Divulgação / Comunicação
A9: Acessibilidade, comunicação e divulgação acessíveis | B9: 0.2 | C9: VALOR DO PROJETO | D9: Todos os projetos. | E9: Gastos proporcionalmente à captação. Inclui consultor/coordenador de acessibilidade e equipe treinada para atender PcD durante o evento. | F9: IN MinC 29/2026 – custos vinculados | G9: ☐ conferido no texto oficial em ___/___/2026 | I9: Cachê – maestro / regente | J9: =L_CACHE_MAESTRO | L9: Acessibilidade
A10: Divulgação / comunicação | B10: 0.2 | C10: VALOR DO PROJETO | D10: Todos os projetos. | E10: Inclui assessoria de comunicação, despesas de divulgação e impulsionamento de conteúdo. Materiais e aplicação de marcas passam por aprovação do MinC. | F10: IN MinC 29/2026 – dispositivo sobre divulgação | G10: ☐ conferido no texto oficial em ___/___/2026 | I10: Cachê – palestrante / conferencista | J10: =L_CACHE_PALESTRA | L10: Custos administrativos
A11: Remuneração de captação – percentual | B11: 0.1 | C11: VALOR DO PROJETO | D11: Quem contrata serviço de captação. | E11: Paga proporcionalmente ao valor efetivamente captado. Serviço deve ser prestado ao PROPONENTE; é proibido pagar serviço prestado ao incentivador. | F11: IN MinC 29/2026 – remuneração de captação | G11: ☐ conferido no texto oficial em ___/___/2026 | I11: Remuneração do proponente | L11: Captação de recursos
A12: Remuneração de captação – teto em reais | B12: 150000 | C12: valor absoluto | D12: Idem. | E12: Vale o MENOR entre 10% do valor do projeto e R$ 150.000,00. | F12: IN MinC 29/2026 – remuneração de captação | G12: ☐ conferido no texto oficial em ___/___/2026 | I12: Custos de administração | L12: Encerramento
A13: Cachê – artista solo (por apresentação) | B13: 25000 | C13: por apresentação | D13: Pago com recurso incentivado. | E13: Valores maiores: só com outras fontes ou mediante apreciação da CNIC. | F13: IN MinC 29/2026 – limites de cachê | G13: ☐ conferido no texto oficial em ___/___/2026 | I13: Divulgação / comunicação
A14: Cachê – grupo / coletivo (por apresentação) | B14: 50000 | C14: por apresentação | D14: Idem. | E14: Idem. | F14: IN MinC 29/2026 – limites de cachê | G14: ☐ conferido no texto oficial em ___/___/2026 | I14: Acessibilidade / comunicação e divulgação acessíveis
A15: Cachê – músico de orquestra | B15: 5000 | C15: por apresentação | D15: Idem. | E15: Idem. | F15: IN MinC 29/2026 – limites de cachê | G15: ☐ conferido no texto oficial em ___/___/2026 | I15: Remuneração de captação
A16: Cachê – maestro / regente | B16: 25000 | C16: por apresentação | D16: Idem. | E16: Idem. | F16: IN MinC 29/2026 – limites de cachê | G16: ☐ conferido no texto oficial em ___/___/2026 | I16: Tributos e encargos
A17: Cachê – palestrante / conferencista | B17: 5000 | C17: por participação | D17: Idem. | E17: Idem. | F17: IN MinC 29/2026 – limites de cachê | G17: ☐ conferido no texto oficial em ___/___/2026 | I17: Outros (explique na observação)
A18: Primeiro projeto no Pronac – dispensa de comprovar atuação cultural | B18: 200000 | C18: VALOR DO PROJETO (confira o termo exato) | D18: Proponente que apresenta seu PRIMEIRO projeto ao Pronac. | E18: Dispensa SOMENTE a comprovação de atuação na área cultural. NÃO dispensa cadastro, documentos, orçamento, acessibilidade, democratização nem análise técnica. Acima do limite: precisa comprovar atuação (portfólio no Salic). | F18: IN MinC 29/2026 – dispositivo sobre comprovação de atuação | G18: ☐ conferido no texto oficial em ___/___/2026
A19: Distribuição gratuita promocional – patrocinador (máximo) | B19: 0.1 | C19: total de ingressos/produtos | D19: Projetos com produtos/ingressos. | F19: IN MinC 29/2026 – plano de distribuição | G19: ☐ conferido no texto oficial em ___/___/2026
A20: Distribuição gratuita promocional – proponente/divulgação (máximo) | B20: 0.1 | C20: total de ingressos/produtos | D20: Idem. | F20: IN MinC 29/2026 – plano de distribuição | G20: ☐ conferido no texto oficial em ___/___/2026
A21: Distribuição gratuita social/educativa (mínimo) | B21: 0.1 | C21: total de ingressos/produtos | D21: Idem. | F21: IN MinC 29/2026 – plano de distribuição | G21: ☐ conferido no texto oficial em ___/___/2026
A22: Comercialização a preço popular (mínimo) | B22: 0.2 | C22: total de ingressos/produtos | D22: Idem. | F22: IN MinC 29/2026 – plano de distribuição | G22: ☐ conferido no texto oficial em ___/___/2026
A23: Preço popular – valor máximo | B23: 50 | C23: por ingresso/produto | D23: Idem. | F23: IN MinC 29/2026 – plano de distribuição | G23: ☐ conferido no texto oficial em ___/___/2026
A24: Preço médio do ingresso (máximo) – CONFIRA | B24: 250 | C24: média dos ingressos comercializados | D24: Idem. | E24: Valor encontrado em fontes secundárias. CONFIRA no texto oficial antes de usar. | F24: IN MinC 29/2026 – plano de distribuição | G24: ☐ conferido no texto oficial em ___/___/2026
A25: Pessoa física – projetos ativos | B25: 2 | C25: quantidade | D25: Proponente PF. | E25: Teto global na linha abaixo. | F25: IN MinC 29/2026 – limites por proponente | G25: ☐ conferido no texto oficial em ___/___/2026
A26: Pessoa física – teto global | B26: 500000 | C26: soma dos projetos ativos | D26: Proponente PF. | F26: IN MinC 29/2026 – limites por proponente | G26: ☐ conferido no texto oficial em ___/___/2026
A27: MEI – projetos ativos | B27: 4 | C27: quantidade | D27: Proponente MEI. | F27: IN MinC 29/2026 – limites por proponente | G27: ☐ conferido no texto oficial em ___/___/2026
A28: MEI – teto global | B28: 1500000 | C28: soma dos projetos ativos | D28: Proponente MEI. | F28: IN MinC 29/2026 – limites por proponente | G28: ☐ conferido no texto oficial em ___/___/2026
A29: Demais pessoas jurídicas – projetos ativos | B29: 10 | C29: quantidade | D29: Demais PJ. | E29: 2026: reduzido de 16 para 10; não há mais limite separado para optantes do Simples. | F29: IN MinC 29/2026 – limites por proponente | G29: ☐ conferido no texto oficial em ___/___/2026
A30: Demais pessoas jurídicas – teto global | B30: 15000000 | C30: soma dos projetos ativos | D30: Demais PJ. | E30: Existem regras específicas (ex.: planos anuais, patrimônio, regiões). Confira. | F30: IN MinC 29/2026 – limites por proponente | G30: ☐ conferido no texto oficial em ___/___/2026
A31: Margem de alerta amarelo (a partir de X% do limite) | B31: 0.9 | C31: — | D31: Configuração do kit (não é regra da IN). | E31: Ex.: 0,90 → acima de 90% do limite aparece 🟡 VERIFICAR. | F31: Configuração interna | G31: ☐ conferido no texto oficial em ___/___/2026

Sheet MAPA DO PROJETO
A1: PLANILHA 1 — MAPA DO PROJETO
A2: Preencha a coluna C. A coluna D mostra se o campo está preenchido e quantos caracteres tem. Escreva para o seu projeto — nada de texto genérico copiado.
A4: Campo | B4: Pergunta que o campo responde | C4: SUA RESPOSTA | D4: Status | E4: Nº de caracteres
A5: Nome do projeto | B5: Como o projeto se chama? Curto, claro, sem siglas soltas. | D5: =IF(LEN(TRIM(C5))=0,"🔴 VAZIO",IF(LEN(TRIM(C5))<40,"🟡 MUITO CURTO","🟢 PREENCHIDO")) | E5: =LEN(C5)
A6: Área cultural | B6: Qual a área (ex.: artes cênicas, música, audiovisual, patrimônio, artes visuais, humanidades…)? | D6: =IF(LEN(TRIM(C6))=0,"🔴 VAZIO",IF(LEN(TRIM(C6))<40,"🟡 MUITO CURTO","🟢 PREENCHIDO")) | E6: =LEN(C6)
A7: Segmento | B7: Qual o segmento dentro da área? Ele define enquadramento (art. 18 ou art. 26 da Lei 8.313/1991). | D7: =IF(LEN(TRIM(C7))=0,"🔴 VAZIO",IF(LEN(TRIM(C7))<40,"🟡 MUITO CURTO","🟢 PREENCHIDO")) | E7: =LEN(C7)
A8: Resumo | B8: Em 5 linhas: O QUÊ + ONDE + QUANDO + PARA QUEM + COMO. | D8: =IF(LEN(TRIM(C8))=0,"🔴 VAZIO",IF(LEN(TRIM(C8))<40,"🟡 MUITO CURTO","🟢 PREENCHIDO")) | E8: =LEN(C8)
A9: Objeto (o que será entregue) | B9: Qual é a entrega principal? (ex.: 8 apresentações gratuitas de teatro de rua). | D9: =IF(LEN(TRIM(C9))=0,"🔴 VAZIO",IF(LEN(TRIM(C9))<40,"🟡 MUITO CURTO","🟢 PREENCHIDO")) | E9: =LEN(C9)
A10: Objetivo geral | B10: Qual a grande mudança/resultado cultural que o projeto busca? (1 frase, verbo no infinitivo). | D10: =IF(LEN(TRIM(C10))=0,"🔴 VAZIO",IF(LEN(TRIM(C10))<40,"🟡 MUITO CURTO","🟢 PREENCHIDO")) | E10: =LEN(C10)
A11: Objetivos específicos | B11: 3 a 5 objetivos mensuráveis. Cada um vira META e PRODUTO. | D11: =IF(LEN(TRIM(C11))=0,"🔴 VAZIO",IF(LEN(TRIM(C11))<40,"🟡 MUITO CURTO","🟢 PREENCHIDO")) | E11: =LEN(C11)
A12: Justificativa | B12: Por que este projeto, neste lugar, agora? Qual a lacuna? Qual a relação com a Lei 8.313/1991 (art. 1º)? | D12: =IF(LEN(TRIM(C12))=0,"🔴 VAZIO",IF(LEN(TRIM(C12))<40,"🟡 MUITO CURTO","🟢 PREENCHIDO")) | E12: =LEN(C12)
A13: Metodologia | B13: Como será feito, etapa por etapa? Quem faz o quê? Cada etapa precisa ter despesa no orçamento. | D13: =IF(LEN(TRIM(C13))=0,"🔴 VAZIO",IF(LEN(TRIM(C13))<40,"🟡 MUITO CURTO","🟢 PREENCHIDO")) | E13: =LEN(C13)
A14: Público-alvo | B14: Quem é o público (perfil, faixa etária, território)? Quantas pessoas? | D14: =IF(LEN(TRIM(C14))=0,"🔴 VAZIO",IF(LEN(TRIM(C14))<40,"🟡 MUITO CURTO","🟢 PREENCHIDO")) | E14: =LEN(C14)
A15: Beneficiários | B15: Quem recebe gratuidade, formação, acesso? Escolas, comunidades, instituições? | D15: =IF(LEN(TRIM(C15))=0,"🔴 VAZIO",IF(LEN(TRIM(C15))<40,"🟡 MUITO CURTO","🟢 PREENCHIDO")) | E15: =LEN(C15)
A16: Produtos | B16: Lista dos produtos culturais (apresentação, livro, oficina, exposição, vídeo…) com quantidades. | D16: =IF(LEN(TRIM(C16))=0,"🔴 VAZIO",IF(LEN(TRIM(C16))<40,"🟡 MUITO CURTO","🟢 PREENCHIDO")) | E16: =LEN(C16)
... A24: Outras fontes de recurso | B24: Existe dinheiro/apoio além do incentivo? Está confirmado? Qual despesa ele paga? | D24: =IF(LEN(TRIM(C24))=0,"🔴 VAZIO",IF(LEN(TRIM(C24))<40,"🟡 MUITO CURTO","🟢 PREENCHIDO")) | E24: =LEN(C24)
A26: Campos preenchidos | C26: =COUNTIF(D5:D24,"🟢*")&" de 20"

Sheet ORÇAMENTO
A1: PLANILHA 2 — ORÇAMENTO ANALÍTICO
A2: Colunas A–J: o que vai para o Salic. Colunas K–O (cinza): SUAS conferências. Colunas P–Q: alertas automáticos. Regra: se não consegue explicar por que a despesa existe, não coloque.
A3: Total incentivo (Rouanet) | C3: =SUMIFS(G8:G207,H8:H207,"Incentivo*") | E3: Linhas com alerta 🔴 | G3: =COUNTIF(Q8:Q207,"*🔴*")
A4: Total outras fontes | C4: =SUMIFS(G8:G207,H8:H207,"Outras*") | E4: Linhas com alerta 🟡 | G4: =COUNTIF(Q8:Q207,"*🟡*")
A5: TOTAL GERAL | C5: =C3+C4 | E5: Linhas 🟢 conferidas | G5: =COUNTIF(Q8:Q207,"🟢*")
A7: Etapa | B7: Item | C7: Descrição | D7: Unidade | E7: Quantidade | F7: Valor unitário | G7: Valor total | H7: Fonte | I7: Fornecedor | J7: Observação | K7: Categoria de limite | L7: Pessoa vinculada ao proponente? (cônjuge, companheiro, coligada, sócio em comum) | M7: POR QUE ESSA DESPESA EXISTE? (vínculo com a metodologia) | N7: Preço de mercado conferido? | O7: Esta despesa é paga também por outra fonte? | P7: % do fornecedor sobre o VALOR CAPTADO | Q7: ALERTAS AUTOMÁTICOS
G8: =IF(OR(E8="",F8=""),"",E8*F8) | P8: =IF(OR(I8="",G8="",LEFT(H8,9)<>"Incentivo",VALOR_CAPTADO=0),"",SUMIFS($G$8:$G$207,$I$8:$I$207,I8,$H$8:$H$207,"Incentivo*")/VALOR_CAPTADO) | Q8: =IF(AND(B8="",G8=""),"",IF(IF(AND(B8="",G8=""),"",IF(OR(E8="",F8=""),"🟡 Falta quantidade ou valor. ","")&IF(H8="","🟡 Informe a fonte. ","")&IF(K8="","🟡 Classifique a categoria de limite. ","")&IF(TRIM(M8)="","🔴 Sem justificativa de vínculo: se não explica, não coloque. ","")&IF(N8<>"Sim","🟡 Preço de mercado não conferido. ","")&IF(O8="Sim","🔴 Possível DUPLA COBERTURA: a mesma despesa não pode ser paga duas vezes. ","")&IF(AND(L8="Sim",K8<>"Remuneração do proponente"),"🟡 Pessoa vinculada: este valor SOMA no limite de remuneração do proponente. ","")&IF(P8="","",IF(P8>L_FORNECEDOR,"🔴 Fornecedor acima do limite sobre o valor captado (confira exceções). ",IF(P8>=L_FORNECEDOR*MARGEM,"🟡 Fornecedor perto do limite. ","")))&IF(AND(LEFT(K8,5)="Cachê",F8<>""),IF(F8>IFERROR(VLOOKUP(K8,TAB_CATEGORIAS,2,FALSE),9E+99),"🔴 Cachê acima do limite: só com outras fontes ou apreciação da CNIC. ",""),"")&IF(AND(LEFT(H8,6)="Outras",K8<>""),"🟡 Outras fontes: confirme que o recurso existe e está comprometido. ",""))="","🟢 CONFERIDO",IF(AND(B8="",G8=""),"",IF(OR(E8="",F8=""),"🟡 Falta quantidade ou valor. ","")&IF(H8="","🟡 Informe a fonte. ","")&IF(K8="","🟡 Classifique a categoria de limite. ","")&IF(TRIM(M8)="","🔴 Sem justificativa de vínculo: se não explica, não coloque. ","")&IF(N8<>"Sim","🟡 Preço de mercado não conferido. ","")&IF(O8="Sim","🔴 Possível DUPLA COBERTURA: a mesma despesa não pode ser paga duas vezes. ","")&IF(AND(L8="Sim",K8<>"Remuneração do proponente"),"🟡 Pessoa vinculada: este valor SOMA no limite de remuneração do proponente. ","")&IF(P8="","",IF(P8>L_FORNECEDOR,"🔴 Fornecedor acima do limite sobre o valor captado (confira exceções). ",IF(P8>=L_FORNECEDOR*MARGEM,"🟡 Fornecedor perto do limite. ","")))&IF(AND(LEFT(K8,5)="Cachê",F8<>""),IF(F8>IFERROR(VLOOKUP(K8,TAB_CATEGORIAS,2,FALSE),9E+99),"🔴 Cachê acima do limite: só com outras fontes ou apreciação da CNIC. ",""),"")&IF(AND(LEFT(H8,6)="Outras",K8<>""),"🟡 Outras fontes: confirme que o recurso existe e está comprometido. ",""))))
G9: =IF(OR(E9="",F9=""),"",E9*F9) | P9: =IF(OR(I9="",G9="",LEFT(H9,9)<>"Incentivo",VALOR_CAPTADO=0),"",SUMIFS($G$8:$G$207,$I$8:$I$207,I9,$H$8:$H$207,"Incentivo*")/VALOR_CAPTADO) | Q9: =IF(AND(B9="",G9=""),"",IF(IF(AND(B9="",G9=""),"",IF(OR(E9="",F9=""),"🟡 Falta quantidade ou valor. ","")&IF(H9="","🟡 Informe a fonte. ","")&IF(K9="","🟡 Classifique a categoria de limite. ","")&IF(TRIM(M9)="","🔴 Sem justificativa de vínculo: se não explica, não coloque. ","")&IF(N9<>"Sim","🟡 Preço de mercado não conferido. ","")&IF(O9="Sim","🔴 Possível DUPLA COBERTURA: a mesma despesa não pode ser paga duas vezes. ","")&IF(AND(L9="Sim",K9<>"Remuneração do proponente"),"🟡 Pessoa vinculada: este valor SOMA no limite de remuneração do proponente. ","")&IF(P9="","",IF(P9>L_FORNECEDOR,"🔴 Fornecedor acima do limite sobre o valor captado (confira exceções). ",IF(P9>=L_FORNECEDOR*MARGEM,"🟡 Fornecedor perto do limite. ","")))&IF(AND(LEFT(K9,5)="Cachê",F9<>""),IF(F9>IFERROR(VLOOKUP(K9,TAB_CATEGORIAS,2,FALSE),9E+99),"🔴 Cachê acima do limite: só com outras fontes ou apreciação da CNIC. ",""),"")&IF(AND(LEFT(H9,6)="Outras",K9<>""),"🟡 Outras fontes: confirme que o recurso existe e está comprometido. ",""))="","🟢 CONFERIDO",IF(AND(B9="",G9=""),"",IF(OR(E9="",F9=""),"🟡 Falta quantidade ou valor. ","")&IF(H9="","🟡 Informe a fonte. ","")&IF(K9="","🟡 Classifique a categoria de limite. ","")&IF(TRIM(M9)="","🔴 Sem justificativa de vínculo: se não explica, não coloque. ","")&IF(N9<>"Sim","🟡 Preço de mercado não conferido. ","")&IF(O9="Sim","🔴 Possível DUPLA COBERTURA: a mesma despesa não pode ser paga duas vezes. ","")&IF(AND(L9="Sim",K9<>"Remuneração do proponente"),"🟡 Pessoa vinculada: este valor SOMA no limite de remuneração do proponente. ","")&IF(P9="","",IF(P9>L_FORNECEDOR,"🔴 Fornecedor acima do limite sobre o valor captado (confira exceções). ",IF(P9>=L_FORNECEDOR*MARGEM,"🟡 Fornecedor perto do limite. ","")))&IF(AND(LEFT(K9,5)="Cachê",F9<>""),IF(F9>IFERROR(VLOOKUP(K9,TAB_CATEGORIAS,2,FALSE),9E+99),"🔴 Cachê acima do limite: só com outras fontes ou apreciação da CNIC. ",""),"")&IF(AND(LEFT(H9,6)="Outras",K9<>""),"🟡 Outras fontes: confirme que o recurso existe e está comprometido. ",""))))
G10: =IF(OR(E10="",F10=""),"",E10*F10) | P10: =IF(OR(I10="",G10="",LEFT(H10,9)<>"Incentivo",VALOR_CAPTADO=0),"",SUMIFS($G$8:$G$207,$I$8:$I$207,I10,$H$8:$H$207,"Incentivo*")/VALOR_CAPTADO) | Q10: =IF(AND(B10="",G10=""),"",IF(IF(AND(B10="",G10=""),"",IF(OR(E10="",F10=""),"🟡 Falta quantidade ou valor. ","")&IF(H10="","🟡 Informe a fonte. ","")&IF(K10="","🟡 Classifique a categoria de limite. ","")&IF(TRIM(M10)="","🔴 Sem justificativa de vínculo: se não explica, não coloque. ","")&IF(N10<>"Sim","🟡 Preço de mercado não conferido. ","")&IF(O10="Sim","🔴 Possível DUPLA COBERTURA: a mesma despesa não pode ser paga duas vezes. ","")&IF(AND(L10="Sim",K10<>"Remuneração do proponente"),"🟡 Pessoa vinculada: este valor SOMA no limite de remuneração do proponente. ","")&IF(P10="","",IF(P10>L_FORNECEDOR,"🔴 Fornecedor acima do limite sobre o valor captado (confira exceções). ",IF(P10>=L_FORNECEDOR*MARGEM,"🟡 Fornecedor perto do limite. ","")))&IF(AND(LEFT(K10,5)="Cachê",F10<>""),IF(F10>IFERROR(VLOOKUP(K10,TAB_CATEGORIAS,2,FALSE),9E+99),"🔴 Cachê acima do limite: só com outras fontes ou apreciação da CNIC. ",""),"")&IF(AND(LEFT(H10,6)="Outras",K10<>""),"🟡 Outras fontes: confirme que o recurso existe e está comprometido. ",""))="","🟢 CONFERIDO",IF(AND(B10="",G10=""),"",IF(OR(E10="",F10=""),"🟡 Falta quantidade ou valor. ","")&IF(H10="","🟡 Informe a fonte. ","")&IF(K10="","🟡 Classifique a categoria de limite. ","")&IF(TRIM(M10)="","🔴 Sem justificativa de vínculo: se não explica, não coloque. ","")&IF(N10<>"Sim","🟡 Preço de mercado não conferido. ","")&IF(O10="Sim","🔴 Possível DUPLA COBERTURA: a mesma despesa não pode ser paga duas vezes. ","")&IF(AND(L10="Sim",K10<>"Remuneração do proponente"),"🟡 Pessoa vinculada: este valor SOMA no limite de remuneração do proponente. ","")&IF(P10="","",IF(P10>L_FORNECEDOR,"🔴 Fornecedor acima do limite sobre o valor captado (confira exceções). ",IF(P10>=L_FORNECEDOR*MARGEM,"🟡 Fornecedor perto do limite. ","")))&IF(AND(LEFT(K10,5)="Cachê",F10<>""),IF(F10>IFERROR(VLOOKUP(K10,TAB_CATEGORIAS,2,FALSE),9E+99),"🔴 Cachê acima do limite: só com outras fontes ou apreciação da CNIC. ",""),"")&IF(AND(LEFT(H10,6)="Outras",K10<>""),"🟡 Outras fontes: confirme que o recurso existe e está comprometido. ",""))))
G11: =IF(OR(E11="",F11=""),"",E11*F11) | P11: =IF(OR(I11="",G11="",LEFT(H11,9)<>"Incentivo",VALOR_CAPTADO=0),"",SUMIFS($G$8:$G$207,$I$8:$I$207,I11,$H$8:$H$207,"Incentivo*")/VALOR_CAPTADO) | Q11: =IF(AND(B11="",G11=""),"",IF(IF(AND(B11="",G11=""),"",IF(OR(E11="",F11=""),"🟡 Falta quantidade ou valor. ","")&IF(H11="","🟡 Informe a fonte. ","")&IF(K11="","🟡 Classifique a categoria de limite. ","")&IF(TRIM(M11)="","🔴 Sem justificativa de vínculo: se não explica, não coloque. ","")&IF(N11<>"Sim","🟡 Preço de mercado não conferido. ","")&IF(O11="Sim","🔴 Possível DUPLA COBERTURA: a mesma despesa não pode ser paga duas vezes. ","")&IF(AND(L11="Sim",K11<>"Remuneração do proponente"),"🟡 Pessoa vinculada: este valor SOMA no limite de remuneração do proponente. ","")&IF(P11="","",IF(P11>L_FORNECEDOR,"🔴 Fornecedor acima do limite sobre o valor captado (confira exceções). ",IF(P11>=L_FORNECEDOR*MARGEM,"🟡 Fornecedor perto do limite. ","")))&IF(AND(LEFT(K11,5)="Cachê",F11<>""),IF(F11>IFERROR(VLOOKUP(K11,TAB_CATEGORIAS,2,FALSE),9E+99),"🔴 Cachê acima do limite: só com outras fontes ou apreciação da CNIC. ",""),"")&IF(AND(LEFT(H11,6)="Outras",K11<>""),"🟡 Outras fontes: confirme que o recurso existe e está comprometido. ",""))="","🟢 CONFERIDO",IF(AND(B11="",G11=""),"",IF(OR(E11="",F11=""),"🟡 Falta quantidade ou valor. ","")&IF(H11="","🟡 Informe a fonte. ","")&IF(K11="","🟡 Classifique a categoria de limite. ","")&IF(TRIM(M11)="","🔴 Sem justificativa de vínculo: se não explica, não coloque. ","")&IF(N11<>"Sim","🟡 Preço de mercado não conferido. ","")&IF(O11="Sim","🔴 Possível DUPLA COBERTURA: a mesma despesa não pode ser paga duas vezes. ","")&IF(AND(L11="Sim",K11<>"Remuneração do proponente"),"🟡 Pessoa vinculada: este valor SOMA no limite de remuneração do proponente. ","")&IF(P11="","",IF(P11>L_FORNECEDOR,"🔴 Fornecedor acima do limite sobre o valor captado (confira exceções). ",IF(P11>=L_FORNECEDOR*MARGEM,"🟡 Fornecedor perto do limite. ","")))&IF(AND(LEFT(K11,5)="Cachê",F11<>""),IF(F11>IFERROR(VLOOKUP(K11,TAB_CATEGORIAS,2,FALSE),9E+99),"🔴 Cachê acima do limite: só com outras fontes ou apreciação da CNIC. ",""),"")&IF(AND(LEFT(H11,6)="Outras",K11<>""),"🟡 Outras fontes: confirme que o recurso existe e está comprometido. ",""))))
G12: =IF(OR(E12="",F12=""),"",E12*F12) | P12: =IF(OR(I12="",G12="",LEFT(H12,9)<>"Incentivo",VALOR_CAPTADO=0),"",SUMIFS($G$8:$G$207,$I$8:$I$207,I12,$H$8:$H$207,"Incentivo*")/VALOR_CAPTADO) | Q12: =IF(AND(B12="",G12=""),"",IF(IF(AND(B12="",G12=""),"",IF(OR(E12="",F12=""),"🟡 Falta quantidade ou valor. ","")&IF(H12="","🟡 Informe a fonte. ","")&IF(K12="","🟡 Classifique a categoria de limite. ","")&IF(TRIM(M12)="","🔴 Sem justificativa de vínculo: se não explica, não coloque. ","")&IF(N12<>"Sim","🟡 Preço de mercado não conferido. ","")&IF(O12="Sim","🔴 Possível DUPLA COBERTURA: a mesma despesa não pode ser paga duas vezes. ","")&IF(AND(L12="Sim",K12<>"Remuneração do proponente"),"🟡 Pessoa vinculada: este valor SOMA no limite de remuneração do proponente. ","")&IF(P12="","",IF(P12>L_FORNECEDOR,"🔴 Fornecedor acima do limite sobre o valor captado (confira exceções). ",IF(P12>=L_FORNECEDOR*MARGEM,"🟡 Fornecedor perto do limite. ","")))&IF(AND(LEFT(K12,5)="Cachê",F12<>""),IF(F12>IFERROR(VLOOKUP(K12,TAB_CATEGORIAS,2,FALSE),9E+99),"🔴 Cachê acima do limite: só com outras fontes ou apreciação da CNIC. ",""),"")&IF(AND(LEFT(H12,6)="Outras",K12<>""),"🟡 Outras fontes: confirme que o recurso existe e está comprometido. ",""))="","🟢 CONFERIDO",IF(AND(B12="",G12=""),"",IF(OR(E12="",F12=""),"🟡 Falta quantidade ou valor. ","")&IF(H12="","🟡 Informe a fonte. ","")&IF(K12="","🟡 Classifique a categoria de limite. ","")&IF(TRIM(M12)="","🔴 Sem justificativa de vínculo: se não explica, não coloque. ","")&IF(N12<>"Sim","🟡 Preço de mercado não conferido. ","")&IF(O12="Sim","🔴 Possível DUPLA COBERTURA: a mesma despesa não pode ser paga duas vezes. ","")&IF(AND(L12="Sim",K12<>"Remuneração do proponente"),"🟡 Pessoa vinculada: este valor SOMA no limite de remuneração do proponente. ","")&IF(P12="","",IF(P12>L_FORNECEDOR,"🔴 Fornecedor acima do limite sobre o valor captado (confira exceções). ",IF(P12>=L_FORNECEDOR*MARGEM,"🟡 Fornecedor perto do limite. ","")))&IF(AND(LEFT(K12,5)="Cachê",F12<>""),IF(F12>IFERROR(VLOOKUP(K12,TAB_CATEGORIAS,2,FALSE),9E+99),"🔴 Cachê acima do limite: só com outras fontes ou apreciação da CNIC. ",""),"")&IF(AND(LEFT(H12,6)="Outras",K12<>""),"🟡 Outras fontes: confirme que o recurso existe e está comprometido. ",""))))
G13: =IF(OR(E13="",F13=""),"",E13*F13) | P13: =IF(OR(I13="",G13="",LEFT(H13,9)<>"Incentivo",VALOR_CAPTADO=0),"",SUMIFS($G$8:$G$207,$I$8:$I$207,I13,$H$8:$H$207,"Incentivo*")/VALOR_CAPTADO) | Q13: =IF(AND(B13="",G13=""),"",IF(IF(AND(B13="",G13=""),"",IF(OR(E13="",F13=""),"🟡 Falta quantidade ou valor. ","")&IF(H13="","🟡 Informe a fonte. ","")&IF(K13="","🟡 Classifique a categoria de limite. ","")&IF(TRIM(M13)="","🔴 Sem justificativa de vínculo: se não explica, não coloque. ","")&IF(N13<>"Sim","🟡 Preço de mercado não conferido. ","")&IF(O13="Sim","🔴 Possível DUPLA COBERTURA: a mesma despesa não pode ser paga duas vezes. ","")&IF(AND(L13="Sim",K13<>"Remuneração do proponente"),"🟡 Pessoa vinculada: este valor SOMA no limite de remuneração do proponente. ","")&IF(P13="","",IF(P13>L_FORNECEDOR,"🔴 Fornecedor acima do limite sobre o valor captado (confira exceções). ",IF(P13>=L_FORNECEDOR*MARGEM,"🟡 Fornecedor perto do limite. ","")))&IF(AND(LEFT(K13,5)="Cachê",F13<>""),IF(F13>IFERROR(VLOOKUP(K13,TAB_CATEGORIAS,2,FALSE),9E+99),"🔴 Cachê acima do limite: só com outras fontes ou apreciação da CNIC. ",""),"")&IF(AND(LEFT(H13,6)="Outras",K13<>""),"🟡 Outras fontes: confirme que o recurso existe e está comprometido. ",""))="","🟢 CONFERIDO",IF(AND(B13="",G13=""),"",IF(OR(E13="",F13=""),"🟡 Falta quantidade ou valor. ","")&IF(H13="","🟡 Informe a fonte. ","")&IF(K13="","🟡 Classifique a categoria de limite. ","")&IF(TRIM(M13)="","🔴 Sem justificativa de vínculo: se não explica, não coloque. ","")&IF(N13<>"Sim","🟡 Preço de mercado não conferido. ","")&IF(O13="Sim","🔴 Possível DUPLA COBERTURA: a mesma despesa não pode ser paga duas vezes. ","")&IF(AND(L13="Sim",K13<>"Remuneração do proponente"),"🟡 Pessoa vinculada: este valor SOMA no limite de remuneração do proponente. ","")&IF(P13="","",IF(P13>L_FORNECEDOR,"🔴 Fornecedor acima do limite sobre o valor captado (confira exceções). ",IF(P13>=L_FORNECEDOR*MARGEM,"🟡 Fornecedor perto do limite. ","")))&IF(AND(LEFT(K13,5)="Cachê",F13<>""),IF(F13>IFERROR(VLOOKUP(K13,TAB_CATEGORIAS,2,FALSE),9E+99),"🔴 Cachê acima do limite: só com outras fontes ou apreciação da CNIC. ",""),"")&IF(AND(LEFT(H13,6)="Outras",K13<>""),"🟡 Outras fontes: confirme que o recurso existe e está comprometido. ",""))))
G14: =IF(OR(E14="",F14=""),"",E14*F14) | P14: =IF(OR(I14="",G14="",LEFT(H14,9)<>"Incentivo",VALOR_CAPTADO=0),"",SUMIFS($G$8:$G$207,$I$8:$I$207,I14,$H$8:$H$207,"Incentivo*")/VALOR_CAPTADO) | Q14: =IF(AND(B14="",G14=""),"",IF(IF(AND(B14="",G14=""),"",IF(OR(E14="",F14=""),"🟡 Falta quantidade ou valor. ","")&IF(H14="","🟡 Informe a fonte. ","")&IF(K14="","🟡 Classifique a categoria de limite. ","")&IF(TRIM(M14)="","🔴 Sem justificativa de vínculo: se não explica, não coloque. ","")&IF(N14<>"Sim","🟡 Preço de mercado não conferido. ","")&IF(O14="Sim","🔴 Possível DUPLA COBERTURA: a mesma despesa não pode ser paga duas vezes. ","")&IF(AND(L14="Sim",K14<>"Remuneração do proponente"),"🟡 Pessoa vinculada: este valor SOMA no limite de remuneração do proponente. ","")&IF(P14="","",IF(P14>L_FORNECEDOR,"🔴 Fornecedor acima do limite sobre o valor captado (confira exceções). ",IF(P14>=L_FORNECEDOR*MARGEM,"🟡 Fornecedor perto do limite. ","")))&IF(AND(LEFT(K14,5)="Cachê",F14<>""),IF(F14>IFERROR(VLOOKUP(K14,TAB_CATEGORIAS,2,FALSE),9E+99),"🔴 Cachê acima do limite: só com outras fontes ou apreciação da CNIC. ",""),"")&IF(AND(LEFT(H14,6)="Outras",K14<>""),"🟡 Outras fontes: confirme que o recurso existe e está comprometido. ",""))="","🟢 CONFERIDO",IF(AND(B14="",G14=""),"",IF(OR(E14="",F14=""),"🟡 Falta quantidade ou valor. ","")&IF(H14="","🟡 Informe a fonte. ","")&IF(K14="","🟡 Classifique a categoria de limite. ","")&IF(TRIM(M14)="","🔴 Sem justificativa de vínculo: se não explica, não coloque. ","")&IF(N14<>"Sim","🟡 Preço de mercado não conferido. ","")&IF(O14="Sim","🔴 Possível DUPLA COBERTURA: a mesma despesa não pode ser paga duas vezes. ","")&IF(AND(L14="Sim",K14<>"Remuneração do proponente"),"🟡 Pessoa vinculada: este valor SOMA no limite de remuneração do proponente. ","")&IF(P14="","",IF(P14>L_FORNECEDOR,"🔴 Fornecedor acima do limite sobre o valor captado (confira exceções). ",IF(P14>=L_FORNECEDOR*MARGEM,"🟡 Fornecedor perto do limite. ","")))&IF(AND(LEFT(K14,5)="Cachê",F14<>""),IF(F14>IFERROR(VLOOKUP(K14,TAB_CATEGORIAS,2,FALSE),9E+99),"🔴 Cachê acima do limite: só com outras fontes ou apreciação da CNIC. ",""),"")&IF(AND(LEFT(H14,6)="Outras",K14<>""),"🟡 Outras fontes: confirme que o recurso existe e está comprometido. ",""))))
G15: =IF(OR(E15="",F15=""),"",E15*F15) | P15: =IF(OR(I15="",G15="",LEFT(H15,9)<>"Incentivo",VALOR_CAPTADO=0),"",SUMIFS($G$8:$G$207,$I$8:$I$207,I15,$H$8:$H$207,"Incentivo*")/VALOR_CAPTADO) | Q15: =IF(AND(B15="",G15=""),"",IF(IF(AND(B15="",G15=""),"",IF(OR(E15="",F15=""),"🟡 Falta quantidade ou valor. ","")&IF(H15="","🟡 Informe a fonte. ","")&IF(K15="","🟡 Classifique a categoria de limite. ","")&IF(TRIM(M15)="","🔴 Sem justificativa de vínculo: se não explica, não coloque. ","")&IF(N15<>"Sim","🟡 Preço de mercado não conferido. ","")&IF(O15="Sim","🔴 Possível DUPLA COBERTURA: a mesma despesa não pode ser paga duas vezes. ","")&IF(AND(L15="Sim",K15<>"Remuneração do proponente"),"🟡 Pessoa vinculada: este valor SOMA no limite de remuneração do proponente. ","")&IF(P15="","",IF(P15>L_FORNECEDOR,"🔴 Fornecedor acima do limite sobre o valor captado (confira exceções). ",IF(P15>=L_FORNECEDOR*MARGEM,"🟡 Fornecedor perto do limite. ","")))&IF(AND(LEFT(K15,5)="Cachê",F15<>""),IF(F15>IFERROR(VLOOKUP(K15,TAB_CATEGORIAS,2,FALSE),9E+99),"🔴 Cachê acima do limite: só com outras fontes ou apreciação da CNIC. ",""),"")&IF(AND(LEFT(H15,6)="Outras",K15<>""),"🟡 Outras fontes: confirme que o recurso existe e está comprometido. ",""))="","🟢 CONFERIDO",IF(AND(B15="",G15=""),"",IF(OR(E15="",F15=""),"🟡 Falta quantidade ou valor. ","")&IF(H15="","🟡 Informe a fonte. ","")&IF(K15="","🟡 Classifique a categoria de limite. ","")&IF(TRIM(M15)="","🔴 Sem justificativa de vínculo: se não explica, não coloque. ","")&IF(N15<>"Sim","🟡 Preço de mercado não conferido. ","")&IF(O15="Sim","🔴 Possível DUPLA COBERTURA: a mesma despesa não pode ser paga duas vezes. ","")&IF(AND(L15="Sim",K15<>"Remuneração do proponente"),"🟡 Pessoa vinculada: este valor SOMA no limite de remuneração do proponente. ","")&IF(P15="","",IF(P15>L_FORNECEDOR,"🔴 Fornecedor acima do limite sobre o valor captado (confira exceções). ",IF(P15>=L_FORNECEDOR*MARGEM,"🟡 Fornecedor perto do limite. ","")))&IF(AND(LEFT(K15,5)="Cachê",F15<>""),IF(F15>IFERROR(VLOOKUP(K15,TAB_CATEGORIAS,2,FALSE),9E+99),"🔴 Cachê acima do limite: só com outras fontes ou apreciação da CNIC. ",""),"")&IF(AND(LEFT(H15,6)="Outras",K15<>""),"🟡 Outras fontes: confirme que o recurso existe e está comprometido. ",""))))
G16: =IF(OR(E16="",F16=""),"",E16*F16) | P16: =IF(OR(I16="",G16="",LEFT(H16,9)<>"Incentivo",VALOR_CAPTADO=0),"",SUMIFS($G$8:$G$207,$I$8:$I$207,I16,$H$8:$H$207,"Incentivo*")/VALOR_CAPTADO) | Q16: =IF(AND(B16="",G16=""),"",IF(IF(AND(B16="",G16=""),"",IF(OR(E16="",F16=""),"🟡 Falta quantidade ou valor. ","")&IF(H16="","🟡 Informe a fonte. ","")&IF(K16="","🟡 Classifique a categoria de limite. ","")&IF(TRIM(M16)="","🔴 Sem justificativa de vínculo: se não explica, não coloque. ","")&IF(N16<>"Sim","🟡 Preço de mercado não conferido. ","")&IF(O16="Sim","🔴 Possível DUPLA COBERTURA: a mesma despesa não pode ser paga duas vezes. ","")&IF(AND(L16="Sim",K16<>"Remuneração do proponente"),"🟡 Pessoa vinculada: este valor SOMA no limite de remuneração do proponente. ","")&IF(P16="","",IF(P16>L_FORNECEDOR,"🔴 Fornecedor acima do limite sobre o valor captado (confira exceções). ",IF(P16>=L_FORNECEDOR*MARGEM,"🟡 Fornecedor perto do limite. ","")))&IF(AND(LEFT(K16,5)="Cachê",F16<>""),IF(F16>IFERROR(VLOOKUP(K16,TAB_CATEGORIAS,2,FALSE),9E+99),"🔴 Cachê acima do limite: só com outras fontes ou apreciação da CNIC. ",""),"")&IF(AND(LEFT(H16,6)="Outras",K16<>""),"🟡 Outras fontes: confirme que o recurso existe e está comprometido. ",""))="","🟢 CONFERIDO",IF(AND(B16="",G16=""),"",IF(OR(E16="",F16=""),"🟡 Falta quantidade ou valor. ","")&IF(H16="","🟡 Informe a fonte. ","")&IF(K16="","🟡 Classifique a categoria de limite. ","")&IF(TRIM(M16)="","🔴 Sem justificativa de vínculo: se não explica, não coloque. ","")&IF(N16<>"Sim","🟡 Preço de mercado não conferido. ","")&IF(O16="Sim","🔴 Possível DUPLA COBERTURA: a mesma despesa não pode ser paga duas vezes. ","")&IF(AND(L16="Sim",K16<>"Remuneração do proponente"),"🟡 Pessoa vinculada: este valor SOMA no limite de remuneração do proponente. ","")&IF(P16="","",IF(P16>L_FORNECEDOR,"🔴 Fornecedor acima do limite sobre o valor captado (confira exceções). ",IF(P16>=L_FORNECEDOR*MARGEM,"🟡 Fornecedor perto do limite. ","")))&IF(AND(LEFT(K16,5)="Cachê",F16<>""),IF(F16>IFERROR(VLOOKUP(K16,TAB_CATEGORIAS,2,FALSE),9E+99),"🔴 Cachê acima do limite: só com outras fontes ou apreciação da CNIC. ",""),"")&IF(AND(LEFT(H16,6)="Outras",K16<>""),"🟡 Outras fontes: confirme que o recurso existe e está comprometido. ",""))))
G17: =IF(OR(E17="",F17=""),"",E17*F17) | P17: =IF(OR(I17="",G17="",LEFT(H17,9)<>"Incentivo",VALOR_CAPTADO=0),"",SUMIFS($G$8:$G$207,$I$8:$I$207,I17,$H$8:$H$207,"Incentivo*")/VALOR_CAPTADO) | Q17: =IF(AND(B17="",G17=""),"",IF(IF(AND(B17="",G17=""),"",IF(OR(E17="",F17=""),"🟡 Falta quantidade ou valor. ","")&IF(H17="","🟡 Informe a fonte. ","")&IF(K17="","🟡 Classifique a categoria de limite. ","")&IF(TRIM(M17)="","🔴 Sem justificativa de vínculo: se não explica, não coloque. ","")&IF(N17<>"Sim","🟡 Preço de mercado não conferido. ","")&IF(O17="Sim","🔴 Possível DUPLA COBERTURA: a mesma despesa não pode ser paga duas vezes. ","")&IF(AND(L17="Sim",K17<>"Remuneração do proponente"),"🟡 Pessoa vinculada: este valor SOMA no limite de remuneração do proponente. ","")&IF(P17="","",IF(P17>L_FORNECEDOR,"🔴 Fornecedor acima do limite sobre o valor captado (confira exceções). ",IF(P17>=L_FORNECEDOR*MARGEM,"🟡 Fornecedor perto do limite. ","")))&IF(AND(LEFT(K17,5)="Cachê",F17<>""),IF(F17>IFERROR(VLOOKUP(K17,TAB_CATEGORIAS,2,FALSE),9E+99),"🔴 Cachê acima do limite: só com outras fontes ou apreciação da CNIC. ",""),"")&IF(AND(LEFT(H17,6)="Outras",K17<>""),"🟡 Outras fontes: confirme que o recurso existe e está comprometido. ",""))="","🟢 CONFERIDO",IF(AND(B17="",G17=""),"",IF(OR(E17="",F17=""),"🟡 Falta quantidade ou valor. ","")&IF(H17="","🟡 Informe a fonte. ","")&IF(K17="","🟡 Classifique a categoria de limite. ","")&IF(TRIM(M17)="","🔴 Sem justificativa de vínculo: se não explica, não coloque. ","")&IF(N17<>"Sim","🟡 Preço de mercado não conferido. ","")&IF(O17="Sim","🔴 Possível DUPLA COBERTURA: a mesma despesa não pode ser paga duas vezes. ","")&IF(AND(L17="Sim",K17<>"Remuneração do proponente"),"🟡 Pessoa vinculada: este valor SOMA no limite de remuneração do proponente. ","")&IF(P17="","",IF(P17>L_FORNECEDOR,"🔴 Fornecedor acima do limite sobre o valor captado (confira exceções). ",IF(P17>=L_FORNECEDOR*MARGEM,"🟡 Fornecedor perto do limite. ","")))&IF(AND(LEFT(K17,5)="Cachê",F17<>""),IF(F17>IFERROR(VLOOKUP(K17,TAB_CATEGORIAS,2,FALSE),9E+99),"🔴 Cachê acima do limite: só com outras fontes ou apreciação da CNIC. ",""),"")&IF(AND(LEFT(H17,6)="Outras",K17<>""),"🟡 Outras fontes: confirme que o recurso existe e está comprometido. ",""))))
G18: =IF(OR(E18="",F18=""),"",E18*F18) | P18: =IF(OR(I18="",G18="",LEFT(H18,9)<>"Incentivo",VALOR_CAPTADO=0),"",SUMIFS($G$8:$G$207,$I$8:$I$207,I18,$H$8:$H$207,"Incentivo*")/VALOR_CAPTADO) | Q18: =IF(AND(B18="",G18=""),"",IF(IF(AND(B18="",G18=""),"",IF(OR(E18="",F18=""),"🟡 Falta quantidade ou valor. ","")&IF(H18="","🟡 Informe a fonte. ","")&IF(K18="","🟡 Classifique a categoria de limite. ","")&IF(TRIM(M18)="","🔴 Sem justificativa de vínculo: se não explica, não coloque. ","")&IF(N18<>"Sim","🟡 Preço de mercado não conferido. ","")&IF(O18="Sim","🔴 Possível DUPLA COBERTURA: a mesma despesa não pode ser paga duas vezes. ","")&IF(AND(L18="Sim",K18<>"Remuneração do proponente"),"🟡 Pessoa vinculada: este valor SOMA no limite de remuneração do proponente. ","")&IF(P18="","",IF(P18>L_FORNECEDOR,"🔴 Fornecedor acima do limite sobre o valor captado (confira exceções). ",IF(P18>=L_FORNECEDOR*MARGEM,"🟡 Fornecedor perto do limite. ","")))&IF(AND(LEFT(K18,5)="Cachê",F18<>""),IF(F18>IFERROR(VLOOKUP(K18,TAB_CATEGORIAS,2,FALSE),9E+99),"🔴 Cachê acima do limite: só com outras fontes ou apreciação da CNIC. ",""),"")&IF(AND(LEFT(H18,6)="Outras",K18<>""),"🟡 Outras fontes: confirme que o recurso existe e está comprometido. ",""))="","🟢 CONFERIDO",IF(AND(B18="",G18=""),"",IF(OR(E18="",F18=""),"🟡 Falta quantidade ou valor. ","")&IF(H18="","🟡 Informe a fonte. ","")&IF(K18="","🟡 Classifique a categoria de limite. ","")&IF(TRIM(M18)="","🔴 Sem justificativa de vínculo: se não explica, não coloque. ","")&IF(N18<>"Sim","🟡 Preço de mercado não conferido. ","")&IF(O18="Sim","🔴 Possível DUPLA COBERTURA: a mesma despesa não pode ser paga duas vezes. ","")&IF(AND(L18="Sim",K18<>"Remuneração do proponente"),"🟡 Pessoa vinculada: este valor SOMA no limite de remuneração do proponente. ","")&IF(P18="","",IF(P18>L_FORNECEDOR,"🔴 Fornecedor acima do limite sobre o valor captado (confira exceções). ",IF(P18>=L_FORNECEDOR*MARGEM,"🟡 Fornecedor perto do limite. ","")))&IF(AND(LEFT(K18,5)="Cachê",F18<>""),IF(F18>IFERROR(VLOOKUP(K18,TAB_CATEGORIAS,2,FALSE),9E+99),"🔴 Cachê acima do limite: só com outras fontes ou apreciação da CNIC. ",""),"")&IF(AND(LEFT(H18,6)="Outras",K18<>""),"🟡 Outras fontes: confirme que o recurso existe e está comprometido. ",""))))
G19: =IF(OR(E19="",F19=""),"",E19*F19) | P19: =IF(OR(I19="",G19="",LEFT(H19,9)<>"Incentivo",VALOR_CAPTADO=0),"",SUMIFS($G$8:$G$207,$I$8:$I$207,I19,$H$8:$H$207,"Incentivo*")/VALOR_CAPTADO) | Q19: =IF(AND(B19="",G19=""),"",IF(IF(AND(B19="",G19=""),"",IF(OR(E19="",F19=""),"🟡 Falta quantidade ou valor. ","")&IF(H19="","🟡 Informe a fonte. ","")&IF(K19="","🟡 Classifique a categoria de limite. ","")&IF(TRIM(M19)="","🔴 Sem justificativa de vínculo: se não explica, não coloque. ","")&IF(N19<>"Sim","🟡 Preço de mercado não conferido. ","")&IF(O19="Sim","🔴 Possível DUPLA COBERTURA: a mesma despesa não pode ser paga duas vezes. ","")&IF(AND(L19="Sim",K19<>"Remuneração do proponente"),"🟡 Pessoa vinculada: este valor SOMA no limite de remuneração do proponente. ","")&IF(P19="","",IF(P19>L_FORNECEDOR,"🔴 Fornecedor acima do limite sobre o valor captado (confira exceções). ",IF(P19>=L_FORNECEDOR*MARGEM,"🟡 Fornecedor perto do limite. ","")))&IF(AND(LEFT(K19,5)="Cachê",F19<>""),IF(F19>IFERROR(VLOOKUP(K19,TAB_CATEGORIAS,2,FALSE),9E+99),"🔴 Cachê acima do limite: só com outras fontes ou apreciação da CNIC. ",""),"")&IF(AND(LEFT(H19,6)="Outras",K19<>""),"🟡 Outras fontes: confirme que o recurso existe e está comprometido. ",""))="","🟢 CONFERIDO",IF(AND(B19="",G19=""),"",IF(OR(E19="",F19=""),"🟡 Falta quantidade ou valor. ","")&IF(H19="","🟡 Informe a fonte. ","")&IF(K19="","🟡 Classifique a categoria de limite. ","")&IF(TRIM(M19)="","🔴 Sem justificativa de vínculo: se não explica, não coloque. ","")&IF(N19<>"Sim","🟡 Preço de mercado não conferido. ","")&IF(O19="Sim","🔴 Possível DUPLA COBERTURA: a mesma despesa não pode ser paga duas vezes. ","")&IF(AND(L19="Sim",K19<>"Remuneração do proponente"),"🟡 Pessoa vinculada: este valor SOMA no limite de remuneração do proponente. ","")&IF(P19="","",IF(P19>L_FORNECEDOR,"🔴 Fornecedor acima do limite sobre o valor captado (confira exceções). ",IF(P19>=L_FORNECEDOR*MARGEM,"🟡 Fornecedor perto do limite. ","")))&IF(AND(LEFT(K19,5)="Cachê",F19<>""),IF(F19>IFERROR(VLOOKUP(K19,TAB_CATEGORIAS,2,FALSE),9E+99),"🔴 Cachê acima do limite: só com outras fontes ou apreciação da CNIC. ",""),"")&IF(AND(LEFT(H19,6)="Outras",K19<>""),"🟡 Outras fontes: confirme que o recurso existe e está comprometido. ",""))))
... G207: =IF(OR(E207="",F207=""),"",E207*F207) | P207: =IF(OR(I207="",G207="",LEFT(H207,9)<>"Incentivo",VALOR_CAPTADO=0),"",SUMIFS($G$8:$G$207,$I$8:$I$207,I207,$H$8:$H$207,"Incentivo*")/VALOR_CAPTADO) | Q207: =IF(AND(B207="",G207=""),"",IF(IF(AND(B207="",G207=""),"",IF(OR(E207="",F207=""),"🟡 Falta quantidade ou valor. ","")&IF(H207="","🟡 Informe a fonte. ","")&IF(K207="","🟡 Classifique a categoria de limite. ","")&IF(TRIM(M207)="","🔴 Sem justificativa de vínculo: se não explica, não coloque. ","")&IF(N207<>"Sim","🟡 Preço de mercado não conferido. ","")&IF(O207="Sim","🔴 Possível DUPLA COBERTURA: a mesma despesa não pode ser paga duas vezes. ","")&IF(AND(L207="Sim",K207<>"Remuneração do proponente"),"🟡 Pessoa vinculada: este valor SOMA no limite de remuneração do proponente. ","")&IF(P207="","",IF(P207>L_FORNECEDOR,"🔴 Fornecedor acima do limite sobre o valor captado (confira exceções). ",IF(P207>=L_FORNECEDOR*MARGEM,"🟡 Fornecedor perto do limite. ","")))&IF(AND(LEFT(K207,5)="Cachê",F207<>""),IF(F207>IFERROR(VLOOKUP(K207,TAB_CATEGORIAS,2,FALSE),9E+99),"🔴 Cachê acima do limite: só com outras fontes ou apreciação da CNIC. ",""),"")&IF(AND(LEFT(H207,6)="Outras",K207<>""),"🟡 Outras fontes: confirme que o recurso existe e está comprometido. ",""))="","🟢 CONFERIDO",IF(AND(B207="",G207=""),"",IF(OR(E207="",F207=""),"🟡 Falta quantidade ou valor. ","")&IF(H207="","🟡 Informe a fonte. ","")&IF(K207="","🟡 Classifique a categoria de limite. ","")&IF(TRIM(M207)="","🔴 Sem justificativa de vínculo: se não explica, não coloque. ","")&IF(N207<>"Sim","🟡 Preço de mercado não conferido. ","")&IF(O207="Sim","🔴 Possível DUPLA COBERTURA: a mesma despesa não pode ser paga duas vezes. ","")&IF(AND(L207="Sim",K207<>"Remuneração do proponente"),"🟡 Pessoa vinculada: este valor SOMA no limite de remuneração do proponente. ","")&IF(P207="","",IF(P207>L_FORNECEDOR,"🔴 Fornecedor acima do limite sobre o valor captado (confira exceções). ",IF(P207>=L_FORNECEDOR*MARGEM,"🟡 Fornecedor perto do limite. ","")))&IF(AND(LEFT(K207,5)="Cachê",F207<>""),IF(F207>IFERROR(VLOOKUP(K207,TAB_CATEGORIAS,2,FALSE),9E+99),"🔴 Cachê acima do limite: só com outras fontes ou apreciação da CNIC. ",""),"")&IF(AND(LEFT(H207,6)="Outras",K207<>""),"🟡 Outras fontes: confirme que o recurso existe e está comprometido. ",""))))

Sheet CRONOGRAMA
A1: PLANILHA 3 — CRONOGRAMA
A2: Não prometa no cronograma aquilo que o orçamento não consegue executar. Toda etapa com atividade precisa ter despesa no ORÇAMENTO (ou justificar por que não tem custo).
A3: Início do projeto
A4: Fim do projeto
A5: Duração total (meses) | B5: =IF(OR(B3="",B4=""),"",DATEDIF(B3,B4,"m")+1) | C5: =IF(B5="","",IF(B5>36,"🔴 Acima de 36 meses de execução (confira a IN)","🟢 Dentro de 36 meses"))
A7: Atividade | B7: Etapa | C7: Início | D7: Fim | E7: Duração (dias) | F7: Responsável | G7: Observações | H7: ALERTAS | I7: =IF($B$3="","",DATE(YEAR($B$3),MONTH($B$3),1)) | J7: =IF(I7="","",EDATE(I7,1)) | K7: =IF(J7="","",EDATE(J7,1)) | L7: =IF(K7="","",EDATE(K7,1)) | M7: =IF(L7="","",EDATE(L7,1)) | N7: =IF(M7="","",EDATE(M7,1)) | O7: =IF(N7="","",EDATE(N7,1)) | P7: =IF(O7="","",EDATE(O7,1)) | Q7: =IF(P7="","",EDATE(P7,1)) | ... Z7: =IF(Y7="","",EDATE(Y7,1))
E8: =IF(OR(C8="",D8=""),"",D8-C8+1) | H8: =IF(A8="","",IF(IF(A8="","",IF(OR(C8="",D8=""),"🟡 Falta data. ",IF(D8<C8,"🔴 Fim antes do início. ","")&IF(OR(AND($B$3<>"",C8<$B$3),AND($B$4<>"",D8>$B$4)),"🔴 Fora do período do projeto. ",""))&IF(B8="","🟡 Informe a etapa. ",IF(COUNTIF('ORÇAMENTO'!$A$8:$A$207,B8)=0,"🟡 Etapa sem despesa no orçamento: quem paga? ",""))&IF(F8="","🟡 Sem responsável. ",""))="","🟢 OK",IF(A8="","",IF(OR(C8="",D8=""),"🟡 Falta data. ",IF(D8<C8,"🔴 Fim antes do início. ","")&IF(OR(AND($B$3<>"",C8<$B$3),AND($B$4<>"",D8>$B$4)),"🔴 Fora do período do projeto. ",""))&IF(B8="","🟡 Informe a etapa. ",IF(COUNTIF('ORÇAMENTO'!$A$8:$A$207,B8)=0,"🟡 Etapa sem despesa no orçamento: quem paga? ",""))&IF(F8="","🟡 Sem responsável. ","")))) | I8: =IF(OR($C8="",$D8="",I$7=""),"",IF(AND($C8<=EOMONTH(I$7,0),$D8>=I$7),"■","")) | J8: =IF(OR($C8="",$D8="",J$7=""),"",IF(AND($C8<=EOMONTH(J$7,0),$D8>=J$7),"■","")) | K8: =IF(OR($C8="",$D8="",K$7=""),"",IF(AND($C8<=EOMONTH(K$7,0),$D8>=K$7),"■","")) | L8: =IF(OR($C8="",$D8="",L$7=""),"",IF(AND($C8<=EOMONTH(L$7,0),$D8>=L$7),"■","")) | M8: =IF(OR($C8="",$D8="",M$7=""),"",IF(AND($C8<=EOMONTH(M$7,0),$D8>=M$7),"■","")) | N8: =IF(OR($C8="",$D8="",N$7=""),"",IF(AND($C8<=EOMONTH(N$7,0),$D8>=N$7),"■","")) | O8: =IF(OR($C8="",$D8="",O$7=""),"",IF(AND($C8<=EOMONTH(O$7,0),$D8>=O$7),"■","")) | P8: =IF(OR($C8="",$D8="",P$7=""),"",IF(AND($C8<=EOMONTH(P$7,0),$D8>=P$7),"■","")) | ... Z8: =IF(OR($C8="",$D8="",Z$7=""),"",IF(AND($C8<=EOMONTH(Z$7,0),$D8>=Z$7),"■",""))
E9: =IF(OR(C9="",D9=""),"",D9-C9+1) | H9: =IF(A9="","",IF(IF(A9="","",IF(OR(C9="",D9=""),"🟡 Falta data. ",IF(D9<C9,"🔴 Fim antes do início. ","")&IF(OR(AND($B$3<>"",C9<$B$3),AND($B$4<>"",D9>$B$4)),"🔴 Fora do período do projeto. ",""))&IF(B9="","🟡 Informe a etapa. ",IF(COUNTIF('ORÇAMENTO'!$A$8:$A$207,B9)=0,"🟡 Etapa sem despesa no orçamento: quem paga? ",""))&IF(F9="","🟡 Sem responsável. ",""))="","🟢 OK",IF(A9="","",IF(OR(C9="",D9=""),"🟡 Falta data. ",IF(D9<C9,"🔴 Fim antes do início. ","")&IF(OR(AND($B$3<>"",C9<$B$3),AND($B$4<>"",D9>$B$4)),"🔴 Fora do período do projeto. ",""))&IF(B9="","🟡 Informe a etapa. ",IF(COUNTIF('ORÇAMENTO'!$A$8:$A$207,B9)=0,"🟡 Etapa sem despesa no orçamento: quem paga? ",""))&IF(F9="","🟡 Sem responsável. ","")))) | I9: =IF(OR($C9="",$D9="",I$7=""),"",IF(AND($C9<=EOMONTH(I$7,0),$D9>=I$7),"■","")) | J9: =IF(OR($C9="",$D9="",J$7=""),"",IF(AND($C9<=EOMONTH(J$7,0),$D9>=J$7),"■","")) | K9: =IF(OR($C9="",$D9="",K$7=""),"",IF(AND($C9<=EOMONTH(K$7,0),$D9>=K$7),"■","")) | L9: =IF(OR($C9="",$D9="",L$7=""),"",IF(AND($C9<=EOMONTH(L$7,0),$D9>=L$7),"■","")) | M9: =IF(OR($C9="",$D9="",M$7=""),"",IF(AND($C9<=EOMONTH(M$7,0),$D9>=M$7),"■","")) | N9: =IF(OR($C9="",$D9="",N$7=""),"",IF(AND($C9<=EOMONTH(N$7,0),$D9>=N$7),"■","")) | O9: =IF(OR($C9="",$D9="",O$7=""),"",IF(AND($C9<=EOMONTH(O$7,0),$D9>=O$7),"■","")) | P9: =IF(OR($C9="",$D9="",P$7=""),"",IF(AND($C9<=EOMONTH(P$7,0),$D9>=P$7),"■","")) | ... Z9: =IF(OR($C9="",$D9="",Z$7=""),"",IF(AND($C9<=EOMONTH(Z$7,0),$D9>=Z$7),"■",""))
E10: =IF(OR(C10="",D10=""),"",D10-C10+1) | H10: =IF(A10="","",IF(IF(A10="","",IF(OR(C10="",D10=""),"🟡 Falta data. ",IF(D10<C10,"🔴 Fim antes do início. ","")&IF(OR(AND($B$3<>"",C10<$B$3),AND($B$4<>"",D10>$B$4)),"🔴 Fora do período do projeto. ",""))&IF(B10="","🟡 Informe a etapa. ",IF(COUNTIF('ORÇAMENTO'!$A$8:$A$207,B10)=0,"🟡 Etapa sem despesa no orçamento: quem paga? ",""))&IF(F10="","🟡 Sem responsável. ",""))="","🟢 OK",IF(A10="","",IF(OR(C10="",D10=""),"🟡 Falta data. ",IF(D10<C10,"🔴 Fim antes do início. ","")&IF(OR(AND($B$3<>"",C10<$B$3),AND($B$4<>"",D10>$B$4)),"🔴 Fora do período do projeto. ",""))&IF(B10="","🟡 Informe a etapa. ",IF(COUNTIF('ORÇAMENTO'!$A$8:$A$207,B10)=0,"🟡 Etapa sem despesa no orçamento: quem paga? ",""))&IF(F10="","🟡 Sem responsável. ","")))) | I10: =IF(OR($C10="",$D10="",I$7=""),"",IF(AND($C10<=EOMONTH(I$7,0),$D10>=I$7),"■","")) | J10: =IF(OR($C10="",$D10="",J$7=""),"",IF(AND($C10<=EOMONTH(J$7,0),$D10>=J$7),"■","")) | K10: =IF(OR($C10="",$D10="",K$7=""),"",IF(AND($C10<=EOMONTH(K$7,0),$D10>=K$7),"■","")) | L10: =IF(OR($C10="",$D10="",L$7=""),"",IF(AND($C10<=EOMONTH(L$7,0),$D10>=L$7),"■","")) | M10: =IF(OR($C10="",$D10="",M$7=""),"",IF(AND($C10<=EOMONTH(M$7,0),$D10>=M$7),"■","")) | N10: =IF(OR($C10="",$D10="",N$7=""),"",IF(AND($C10<=EOMONTH(N$7,0),$D10>=N$7),"■","")) | O10: =IF(OR($C10="",$D10="",O$7=""),"",IF(AND($C10<=EOMONTH(O$7,0),$D10>=O$7),"■","")) | P10: =IF(OR($C10="",$D10="",P$7=""),"",IF(AND($C10<=EOMONTH(P$7,0),$D10>=P$7),"■","")) | ... Z10: =IF(OR($C10="",$D10="",Z$7=""),"",IF(AND($C10<=EOMONTH(Z$7,0),$D10>=Z$7),"■",""))
E11: =IF(OR(C11="",D11=""),"",D11-C11+1) | H11: =IF(A11="","",IF(IF(A11="","",IF(OR(C11="",D11=""),"🟡 Falta data. ",IF(D11<C11,"🔴 Fim antes do início. ","")&IF(OR(AND($B$3<>"",C11<$B$3),AND($B$4<>"",D11>$B$4)),"🔴 Fora do período do projeto. ",""))&IF(B11="","🟡 Informe a etapa. ",IF(COUNTIF('ORÇAMENTO'!$A$8:$A$207,B11)=0,"🟡 Etapa sem despesa no orçamento: quem paga? ",""))&IF(F11="","🟡 Sem responsável. ",""))="","🟢 OK",IF(A11="","",IF(OR(C11="",D11=""),"🟡 Falta data. ",IF(D11<C11,"🔴 Fim antes do início. ","")&IF(OR(AND($B$3<>"",C11<$B$3),AND($B$4<>"",D11>$B$4)),"🔴 Fora do período do projeto. ",""))&IF(B11="","🟡 Informe a etapa. ",IF(COUNTIF('ORÇAMENTO'!$A$8:$A$207,B11)=0,"🟡 Etapa sem despesa no orçamento: quem paga? ",""))&IF(F11="","🟡 Sem responsável. ","")))) | I11: =IF(OR($C11="",$D11="",I$7=""),"",IF(AND($C11<=EOMONTH(I$7,0),$D11>=I$7),"■","")) | J11: =IF(OR($C11="",$D11="",J$7=""),"",IF(AND($C11<=EOMONTH(J$7,0),$D11>=J$7),"■","")) | K11: =IF(OR($C11="",$D11="",K$7=""),"",IF(AND($C11<=EOMONTH(K$7,0),$D11>=K$7),"■","")) | L11: =IF(OR($C11="",$D11="",L$7=""),"",IF(AND($C11<=EOMONTH(L$7,0),$D11>=L$7),"■","")) | M11: =IF(OR($C11="",$D11="",M$7=""),"",IF(AND($C11<=EOMONTH(M$7,0),$D11>=M$7),"■","")) | N11: =IF(OR($C11="",$D11="",N$7=""),"",IF(AND($C11<=EOMONTH(N$7,0),$D11>=N$7),"■","")) | O11: =IF(OR($C11="",$D11="",O$7=""),"",IF(AND($C11<=EOMONTH(O$7,0),$D11>=O$7),"■","")) | P11: =IF(OR($C11="",$D11="",P$7=""),"",IF(AND($C11<=EOMONTH(P$7,0),$D11>=P$7),"■","")) | ... Z11: =IF(OR($C11="",$D11="",Z$7=""),"",IF(AND($C11<=EOMONTH(Z$7,0),$D11>=Z$7),"■",""))
E12: =IF(OR(C12="",D12=""),"",D12-C12+1) | H12: =IF(A12="","",IF(IF(A12="","",IF(OR(C12="",D12=""),"🟡 Falta data. ",IF(D12<C12,"🔴 Fim antes do início. ","")&IF(OR(AND($B$3<>"",C12<$B$3),AND($B$4<>"",D12>$B$4)),"🔴 Fora do período do projeto. ",""))&IF(B12="","🟡 Informe a etapa. ",IF(COUNTIF('ORÇAMENTO'!$A$8:$A$207,B12)=0,"🟡 Etapa sem despesa no orçamento: quem paga? ",""))&IF(F12="","🟡 Sem responsável. ",""))="","🟢 OK",IF(A12="","",IF(OR(C12="",D12=""),"🟡 Falta data. ",IF(D12<C12,"🔴 Fim antes do início. ","")&IF(OR(AND($B$3<>"",C12<$B$3),AND($B$4<>"",D12>$B$4)),"🔴 Fora do período do projeto. ",""))&IF(B12="","🟡 Informe a etapa. ",IF(COUNTIF('ORÇAMENTO'!$A$8:$A$207,B12)=0,"🟡 Etapa sem despesa no orçamento: quem paga? ",""))&IF(F12="","🟡 Sem responsável. ","")))) | I12: =IF(OR($C12="",$D12="",I$7=""),"",IF(AND($C12<=EOMONTH(I$7,0),$D12>=I$7),"■","")) | J12: =IF(OR($C12="",$D12="",J$7=""),"",IF(AND($C12<=EOMONTH(J$7,0),$D12>=J$7),"■","")) | K12: =IF(OR($C12="",$D12="",K$7=""),"",IF(AND($C12<=EOMONTH(K$7,0),$D12>=K$7),"■","")) | L12: =IF(OR($C12="",$D12="",L$7=""),"",IF(AND($C12<=EOMONTH(L$7,0),$D12>=L$7),"■","")) | M12: =IF(OR($C12="",$D12="",M$7=""),"",IF(AND($C12<=EOMONTH(M$7,0),$D12>=M$7),"■","")) | N12: =IF(OR($C12="",$D12="",N$7=""),"",IF(AND($C12<=EOMONTH(N$7,0),$D12>=N$7),"■","")) | O12: =IF(OR($C12="",$D12="",O$7=""),"",IF(AND($C12<=EOMONTH(O$7,0),$D12>=O$7),"■","")) | P12: =IF(OR($C12="",$D12="",P$7=""),"",IF(AND($C12<=EOMONTH(P$7,0),$D12>=P$7),"■","")) | ... Z12: =IF(OR($C12="",$D12="",Z$7=""),"",IF(AND($C12<=EOMONTH(Z$7,0),$D12>=Z$7),"■",""))
E13: =IF(OR(C13="",D13=""),"",D13-C13+1) | H13: =IF(A13="","",IF(IF(A13="","",IF(OR(C13="",D13=""),"🟡 Falta data. ",IF(D13<C13,"🔴 Fim antes do início. ","")&IF(OR(AND($B$3<>"",C13<$B$3),AND($B$4<>"",D13>$B$4)),"🔴 Fora do período do projeto. ",""))&IF(B13="","🟡 Informe a etapa. ",IF(COUNTIF('ORÇAMENTO'!$A$8:$A$207,B13)=0,"🟡 Etapa sem despesa no orçamento: quem paga? ",""))&IF(F13="","🟡 Sem responsável. ",""))="","🟢 OK",IF(A13="","",IF(OR(C13="",D13=""),"🟡 Falta data. ",IF(D13<C13,"🔴 Fim antes do início. ","")&IF(OR(AND($B$3<>"",C13<$B$3),AND($B$4<>"",D13>$B$4)),"🔴 Fora do período do projeto. ",""))&IF(B13="","🟡 Informe a etapa. ",IF(COUNTIF('ORÇAMENTO'!$A$8:$A$207,B13)=0,"🟡 Etapa sem despesa no orçamento: quem paga? ",""))&IF(F13="","🟡 Sem responsável. ","")))) | I13: =IF(OR($C13="",$D13="",I$7=""),"",IF(AND($C13<=EOMONTH(I$7,0),$D13>=I$7),"■","")) | J13: =IF(OR($C13="",$D13="",J$7=""),"",IF(AND($C13<=EOMONTH(J$7,0),$D13>=J$7),"■","")) | K13: =IF(OR($C13="",$D13="",K$7=""),"",IF(AND($C13<=EOMONTH(K$7,0),$D13>=K$7),"■","")) | L13: =IF(OR($C13="",$D13="",L$7=""),"",IF(AND($C13<=EOMONTH(L$7,0),$D13>=L$7),"■","")) | M13: =IF(OR($C13="",$D13="",M$7=""),"",IF(AND($C13<=EOMONTH(M$7,0),$D13>=M$7),"■","")) | N13: =IF(OR($C13="",$D13="",N$7=""),"",IF(AND($C13<=EOMONTH(N$7,0),$D13>=N$7),"■","")) | O13: =IF(OR($C13="",$D13="",O$7=""),"",IF(AND($C13<=EOMONTH(O$7,0),$D13>=O$7),"■","")) | P13: =IF(OR($C13="",$D13="",P$7=""),"",IF(AND($C13<=EOMONTH(P$7,0),$D13>=P$7),"■","")) | ... Z13: =IF(OR($C13="",$D13="",Z$7=""),"",IF(AND($C13<=EOMONTH(Z$7,0),$D13>=Z$7),"■",""))
E14: =IF(OR(C14="",D14=""),"",D14-C14+1) | H14: =IF(A14="","",IF(IF(A14="","",IF(OR(C14="",D14=""),"🟡 Falta data. ",IF(D14<C14,"🔴 Fim antes do início. ","")&IF(OR(AND($B$3<>"",C14<$B$3),AND($B$4<>"",D14>$B$4)),"🔴 Fora do período do projeto. ",""))&IF(B14="","🟡 Informe a etapa. ",IF(COUNTIF('ORÇAMENTO'!$A$8:$A$207,B14)=0,"🟡 Etapa sem despesa no orçamento: quem paga? ",""))&IF(F14="","🟡 Sem responsável. ",""))="","🟢 OK",IF(A14="","",IF(OR(C14="",D14=""),"🟡 Falta data. ",IF(D14<C14,"🔴 Fim antes do início. ","")&IF(OR(AND($B$3<>"",C14<$B$3),AND($B$4<>"",D14>$B$4)),"🔴 Fora do período do projeto. ",""))&IF(B14="","🟡 Informe a etapa. ",IF(COUNTIF('ORÇAMENTO'!$A$8:$A$207,B14)=0,"🟡 Etapa sem despesa no orçamento: quem paga? ",""))&IF(F14="","🟡 Sem responsável. ","")))) | I14: =IF(OR($C14="",$D14="",I$7=""),"",IF(AND($C14<=EOMONTH(I$7,0),$D14>=I$7),"■","")) | J14: =IF(OR($C14="",$D14="",J$7=""),"",IF(AND($C14<=EOMONTH(J$7,0),$D14>=J$7),"■","")) | K14: =IF(OR($C14="",$D14="",K$7=""),"",IF(AND($C14<=EOMONTH(K$7,0),$D14>=K$7),"■","")) | L14: =IF(OR($C14="",$D14="",L$7=""),"",IF(AND($C14<=EOMONTH(L$7,0),$D14>=L$7),"■","")) | M14: =IF(OR($C14="",$D14="",M$7=""),"",IF(AND($C14<=EOMONTH(M$7,0),$D14>=M$7),"■","")) | N14: =IF(OR($C14="",$D14="",N$7=""),"",IF(AND($C14<=EOMONTH(N$7,0),$D14>=N$7),"■","")) | O14: =IF(OR($C14="",$D14="",O$7=""),"",IF(AND($C14<=EOMONTH(O$7,0),$D14>=O$7),"■","")) | P14: =IF(OR($C14="",$D14="",P$7=""),"",IF(AND($C14<=EOMONTH(P$7,0),$D14>=P$7),"■","")) | ... Z14: =IF(OR($C14="",$D14="",Z$7=""),"",IF(AND($C14<=EOMONTH(Z$7,0),$D14>=Z$7),"■",""))
E15: =IF(OR(C15="",D15=""),"",D15-C15+1) | H15: =IF(A15="","",IF(IF(A15="","",IF(OR(C15="",D15=""),"🟡 Falta data. ",IF(D15<C15,"🔴 Fim antes do início. ","")&IF(OR(AND($B$3<>"",C15<$B$3),AND($B$4<>"",D15>$B$4)),"🔴 Fora do período do projeto. ",""))&IF(B15="","🟡 Informe a etapa. ",IF(COUNTIF('ORÇAMENTO'!$A$8:$A$207,B15)=0,"🟡 Etapa sem despesa no orçamento: quem paga? ",""))&IF(F15="","🟡 Sem responsável. ",""))="","🟢 OK",IF(A15="","",IF(OR(C15="",D15=""),"🟡 Falta data. ",IF(D15<C15,"🔴 Fim antes do início. ","")&IF(OR(AND($B$3<>"",C15<$B$3),AND($B$4<>"",D15>$B$4)),"🔴 Fora do período do projeto. ",""))&IF(B15="","🟡 Informe a etapa. ",IF(COUNTIF('ORÇAMENTO'!$A$8:$A$207,B15)=0,"🟡 Etapa sem despesa no orçamento: quem paga? ",""))&IF(F15="","🟡 Sem responsável. ","")))) | I15: =IF(OR($C15="",$D15="",I$7=""),"",IF(AND($C15<=EOMONTH(I$7,0),$D15>=I$7),"■","")) | J15: =IF(OR($C15="",$D15="",J$7=""),"",IF(AND($C15<=EOMONTH(J$7,0),$D15>=J$7),"■","")) | K15: =IF(OR($C15="",$D15="",K$7=""),"",IF(AND($C15<=EOMONTH(K$7,0),$D15>=K$7),"■","")) | L15: =IF(OR($C15="",$D15="",L$7=""),"",IF(AND($C15<=EOMONTH(L$7,0),$D15>=L$7),"■","")) | M15: =IF(OR($C15="",$D15="",M$7=""),"",IF(AND($C15<=EOMONTH(M$7,0),$D15>=M$7),"■","")) | N15: =IF(OR($C15="",$D15="",N$7=""),"",IF(AND($C15<=EOMONTH(N$7,0),$D15>=N$7),"■","")) | O15: =IF(OR($C15="",$D15="",O$7=""),"",IF(AND($C15<=EOMONTH(O$7,0),$D15>=O$7),"■","")) | P15: =IF(OR($C15="",$D15="",P$7=""),"",IF(AND($C15<=EOMONTH(P$7,0),$D15>=P$7),"■","")) | ... Z15: =IF(OR($C15="",$D15="",Z$7=""),"",IF(AND($C15<=EOMONTH(Z$7,0),$D15>=Z$7),"■",""))
E16: =IF(OR(C16="",D16=""),"",D16-C16+1) | H16: =IF(A16="","",IF(IF(A16="","",IF(OR(C16="",D16=""),"🟡 Falta data. ",IF(D16<C16,"🔴 Fim antes do início. ","")&IF(OR(AND($B$3<>"",C16<$B$3),AND($B$4<>"",D16>$B$4)),"🔴 Fora do período do projeto. ",""))&IF(B16="","🟡 Informe a etapa. ",IF(COUNTIF('ORÇAMENTO'!$A$8:$A$207,B16)=0,"🟡 Etapa sem despesa no orçamento: quem paga? ",""))&IF(F16="","🟡 Sem responsável. ",""))="","🟢 OK",IF(A16="","",IF(OR(C16="",D16=""),"🟡 Falta data. ",IF(D16<C16,"🔴 Fim antes do início. ","")&IF(OR(AND($B$3<>"",C16<$B$3),AND($B$4<>"",D16>$B$4)),"🔴 Fora do período do projeto. ",""))&IF(B16="","🟡 Informe a etapa. ",IF(COUNTIF('ORÇAMENTO'!$A$8:$A$207,B16)=0,"🟡 Etapa sem despesa no orçamento: quem paga? ",""))&IF(F16="","🟡 Sem responsável. ","")))) | I16: =IF(OR($C16="",$D16="",I$7=""),"",IF(AND($C16<=EOMONTH(I$7,0),$D16>=I$7),"■","")) | J16: =IF(OR($C16="",$D16="",J$7=""),"",IF(AND($C16<=EOMONTH(J$7,0),$D16>=J$7),"■","")) | K16: =IF(OR($C16="",$D16="",K$7=""),"",IF(AND($C16<=EOMONTH(K$7,0),$D16>=K$7),"■","")) | L16: =IF(OR($C16="",$D16="",L$7=""),"",IF(AND($C16<=EOMONTH(L$7,0),$D16>=L$7),"■","")) | M16: =IF(OR($C16="",$D16="",M$7=""),"",IF(AND($C16<=EOMONTH(M$7,0),$D16>=M$7),"■","")) | N16: =IF(OR($C16="",$D16="",N$7=""),"",IF(AND($C16<=EOMONTH(N$7,0),$D16>=N$7),"■","")) | O16: =IF(OR($C16="",$D16="",O$7=""),"",IF(AND($C16<=EOMONTH(O$7,0),$D16>=O$7),"■","")) | P16: =IF(OR($C16="",$D16="",P$7=""),"",IF(AND($C16<=EOMONTH(P$7,0),$D16>=P$7),"■","")) | ... Z16: =IF(OR($C16="",$D16="",Z$7=""),"",IF(AND($C16<=EOMONTH(Z$7,0),$D16>=Z$7),"■",""))
E17: =IF(OR(C17="",D17=""),"",D17-C17+1) | H17: =IF(A17="","",IF(IF(A17="","",IF(OR(C17="",D17=""),"🟡 Falta data. ",IF(D17<C17,"🔴 Fim antes do início. ","")&IF(OR(AND($B$3<>"",C17<$B$3),AND($B$4<>"",D17>$B$4)),"🔴 Fora do período do projeto. ",""))&IF(B17="","🟡 Informe a etapa. ",IF(COUNTIF('ORÇAMENTO'!$A$8:$A$207,B17)=0,"🟡 Etapa sem despesa no orçamento: quem paga? ",""))&IF(F17="","🟡 Sem responsável. ",""))="","🟢 OK",IF(A17="","",IF(OR(C17="",D17=""),"🟡 Falta data. ",IF(D17<C17,"🔴 Fim antes do início. ","")&IF(OR(AND($B$3<>"",C17<$B$3),AND($B$4<>"",D17>$B$4)),"🔴 Fora do período do projeto. ",""))&IF(B17="","🟡 Informe a etapa. ",IF(COUNTIF('ORÇAMENTO'!$A$8:$A$207,B17)=0,"🟡 Etapa sem despesa no orçamento: quem paga? ",""))&IF(F17="","🟡 Sem responsável. ","")))) | I17: =IF(OR($C17="",$D17="",I$7=""),"",IF(AND($C17<=EOMONTH(I$7,0),$D17>=I$7),"■","")) | J17: =IF(OR($C17="",$D17="",J$7=""),"",IF(AND($C17<=EOMONTH(J$7,0),$D17>=J$7),"■","")) | K17: =IF(OR($C17="",$D17="",K$7=""),"",IF(AND($C17<=EOMONTH(K$7,0),$D17>=K$7),"■","")) | L17: =IF(OR($C17="",$D17="",L$7=""),"",IF(AND($C17<=EOMONTH(L$7,0),$D17>=L$7),"■","")) | M17: =IF(OR($C17="",$D17="",M$7=""),"",IF(AND($C17<=EOMONTH(M$7,0),$D17>=M$7),"■","")) | N17: =IF(OR($C17="",$D17="",N$7=""),"",IF(AND($C17<=EOMONTH(N$7,0),$D17>=N$7),"■","")) | O17: =IF(OR($C17="",$D17="",O$7=""),"",IF(AND($C17<=EOMONTH(O$7,0),$D17>=O$7),"■","")) | P17: =IF(OR($C17="",$D17="",P$7=""),"",IF(AND($C17<=EOMONTH(P$7,0),$D17>=P$7),"■","")) | ... Z17: =IF(OR($C17="",$D17="",Z$7=""),"",IF(AND($C17<=EOMONTH(Z$7,0),$D17>=Z$7),"■",""))
E18: =IF(OR(C18="",D18=""),"",D18-C18+1) | H18: =IF(A18="","",IF(IF(A18="","",IF(OR(C18="",D18=""),"🟡 Falta data. ",IF(D18<C18,"🔴 Fim antes do início. ","")&IF(OR(AND($B$3<>"",C18<$B$3),AND($B$4<>"",D18>$B$4)),"🔴 Fora do período do projeto. ",""))&IF(B18="","🟡 Informe a etapa. ",IF(COUNTIF('ORÇAMENTO'!$A$8:$A$207,B18)=0,"🟡 Etapa sem despesa no orçamento: quem paga? ",""))&IF(F18="","🟡 Sem responsável. ",""))="","🟢 OK",IF(A18="","",IF(OR(C18="",D18=""),"🟡 Falta data. ",IF(D18<C18,"🔴 Fim antes do início. ","")&IF(OR(AND($B$3<>"",C18<$B$3),AND($B$4<>"",D18>$B$4)),"🔴 Fora do período do projeto. ",""))&IF(B18="","🟡 Informe a etapa. ",IF(COUNTIF('ORÇAMENTO'!$A$8:$A$207,B18)=0,"🟡 Etapa sem despesa no orçamento: quem paga? ",""))&IF(F18="","🟡 Sem responsável. ","")))) | I18: =IF(OR($C18="",$D18="",I$7=""),"",IF(AND($C18<=EOMONTH(I$7,0),$D18>=I$7),"■","")) | J18: =IF(OR($C18="",$D18="",J$7=""),"",IF(AND($C18<=EOMONTH(J$7,0),$D18>=J$7),"■","")) | K18: =IF(OR($C18="",$D18="",K$7=""),"",IF(AND($C18<=EOMONTH(K$7,0),$D18>=K$7),"■","")) | L18: =IF(OR($C18="",$D18="",L$7=""),"",IF(AND($C18<=EOMONTH(L$7,0),$D18>=L$7),"■","")) | M18: =IF(OR($C18="",$D18="",M$7=""),"",IF(AND($C18<=EOMONTH(M$7,0),$D18>=M$7),"■","")) | N18: =IF(OR($C18="",$D18="",N$7=""),"",IF(AND($C18<=EOMONTH(N$7,0),$D18>=N$7),"■","")) | O18: =IF(OR($C18="",$D18="",O$7=""),"",IF(AND($C18<=EOMONTH(O$7,0),$D18>=O$7),"■","")) | P18: =IF(OR($C18="",$D18="",P$7=""),"",IF(AND($C18<=EOMONTH(P$7,0),$D18>=P$7),"■","")) | ... Z18: =IF(OR($C18="",$D18="",Z$7=""),"",IF(AND($C18<=EOMONTH(Z$7,0),$D18>=Z$7),"■",""))
E19: =IF(OR(C19="",D19=""),"",D19-C19+1) | H19: =IF(A19="","",IF(IF(A19="","",IF(OR(C19="",D19=""),"🟡 Falta data. ",IF(D19<C19,"🔴 Fim antes do início. ","")&IF(OR(AND($B$3<>"",C19<$B$3),AND($B$4<>"",D19>$B$4)),"🔴 Fora do período do projeto. ",""))&IF(B19="","🟡 Informe a etapa. ",IF(COUNTIF('ORÇAMENTO'!$A$8:$A$207,B19)=0,"🟡 Etapa sem despesa no orçamento: quem paga? ",""))&IF(F19="","🟡 Sem responsável. ",""))="","🟢 OK",IF(A19="","",IF(OR(C19="",D19=""),"🟡 Falta data. ",IF(D19<C19,"🔴 Fim antes do início. ","")&IF(OR(AND($B$3<>"",C19<$B$3),AND($B$4<>"",D19>$B$4)),"🔴 Fora do período do projeto. ",""))&IF(B19="","🟡 Informe a etapa. ",IF(COUNTIF('ORÇAMENTO'!$A$8:$A$207,B19)=0,"🟡 Etapa sem despesa no orçamento: quem paga? ",""))&IF(F19="","🟡 Sem responsável. ","")))) | I19: =IF(OR($C19="",$D19="",I$7=""),"",IF(AND($C19<=EOMONTH(I$7,0),$D19>=I$7),"■","")) | J19: =IF(OR($C19="",$D19="",J$7=""),"",IF(AND($C19<=EOMONTH(J$7,0),$D19>=J$7),"■","")) | K19: =IF(OR($C19="",$D19="",K$7=""),"",IF(AND($C19<=EOMONTH(K$7,0),$D19>=K$7),"■","")) | L19: =IF(OR($C19="",$D19="",L$7=""),"",IF(AND($C19<=EOMONTH(L$7,0),$D19>=L$7),"■","")) | M19: =IF(OR($C19="",$D19="",M$7=""),"",IF(AND($C19<=EOMONTH(M$7,0),$D19>=M$7),"■","")) | N19: =IF(OR($C19="",$D19="",N$7=""),"",IF(AND($C19<=EOMONTH(N$7,0),$D19>=N$7),"■","")) | O19: =IF(OR($C19="",$D19="",O$7=""),"",IF(AND($C19<=EOMONTH(O$7,0),$D19>=O$7),"■","")) | P19: =IF(OR($C19="",$D19="",P$7=""),"",IF(AND($C19<=EOMONTH(P$7,0),$D19>=P$7),"■","")) | ... Z19: =IF(OR($C19="",$D19="",Z$7=""),"",IF(AND($C19<=EOMONTH(Z$7,0),$D19>=Z$7),"■",""))
... E67: =IF(OR(C67="",D67=""),"",D67-C67+1) | H67: =IF(A67="","",IF(IF(A67="","",IF(OR(C67="",D67=""),"🟡 Falta data. ",IF(D67<C67,"🔴 Fim antes do início. ","")&IF(OR(AND($B$3<>"",C67<$B$3),AND($B$4<>"",D67>$B$4)),"🔴 Fora do período do projeto. ",""))&IF(B67="","🟡 Informe a etapa. ",IF(COUNTIF('ORÇAMENTO'!$A$8:$A$207,B67)=0,"🟡 Etapa sem despesa no orçamento: quem paga? ",""))&IF(F67="","🟡 Sem responsável. ",""))="","🟢 OK",IF(A67="","",IF(OR(C67="",D67=""),"🟡 Falta data. ",IF(D67<C67,"🔴 Fim antes do início. ","")&IF(OR(AND($B$3<>"",C67<$B$3),AND($B$4<>"",D67>$B$4)),"🔴 Fora do período do projeto. ",""))&IF(B67="","🟡 Informe a etapa. ",IF(COUNTIF('ORÇAMENTO'!$A$8:$A$207,B67)=0,"🟡 Etapa sem despesa no orçamento: quem paga? ",""))&IF(F67="","🟡 Sem responsável. ","")))) | I67: =IF(OR($C67="",$D67="",I$7=""),"",IF(AND($C67<=EOMONTH(I$7,0),$D67>=I$7),"■","")) | J67: =IF(OR($C67="",$D67="",J$7=""),"",IF(AND($C67<=EOMONTH(J$7,0),$D67>=J$7),"■","")) | K67: =IF(OR($C67="",$D67="",K$7=""),"",IF(AND($C67<=EOMONTH(K$7,0),$D67>=K$7),"■","")) | L67: =IF(OR($C67="",$D67="",L$7=""),"",IF(AND($C67<=EOMONTH(L$7,0),$D67>=L$7),"■","")) | M67: =IF(OR($C67="",$D67="",M$7=""),"",IF(AND($C67<=EOMONTH(M$7,0),$D67>=M$7),"■","")) | N67: =IF(OR($C67="",$D67="",N$7=""),"",IF(AND($C67<=EOMONTH(N$7,0),$D67>=N$7),"■","")) | O67: =IF(OR($C67="",$D67="",O$7=""),"",IF(AND($C67<=EOMONTH(O$7,0),$D67>=O$7),"■","")) | P67: =IF(OR($C67="",$D67="",P$7=""),"",IF(AND($C67<=EOMONTH(P$7,0),$D67>=P$7),"■","")) | ... Z67: =IF(OR($C67="",$D67="",Z$7=""),"",IF(AND($C67<=EOMONTH(Z$7,0),$D67>=Z$7),"■",""))

Sheet DISTRIBUICAO
A1: CALCULADORA F — PLANO DE DISTRIBUIÇÃO E DEMOCRATIZAÇÃO
A2: Para projetos com ingressos ou produtos (livros, CDs, exemplares). Se o seu projeto é 100% gratuito, informe tudo em 'gratuita social/educativa' e 'demais gratuitos' e registre isso no Salic.
A4: Total de ingressos / produtos previstos
A6: Faixa | B6: Quantidade | C6: VALOR INFORMADO (%) | D6: BASE DE CÁLCULO | E6: LIMITE APLICÁVEL | F6: Tipo de limite | G6: STATUS | H6: OBSERVAÇÃO
A7: Gratuita promocional – patrocinador | C7: =IF(OR($C$4="",$C$4=0,B7=""),"",B7/$C$4) | D7: Total de ingressos/produtos | E7: =L_DIST_PATROC | F7: máximo | G7: =IF(C7="","",IF(C7>E7,"🔴 ACIMA DO LIMITE",IF(C7>=E7*MARGEM,"🟡 VERIFICAR","🟢 DENTRO DO LIMITE"))) | H7: Até o limite; é promocional, não conta como democratização.
A8: Gratuita promocional – proponente (divulgação) | C8: =IF(OR($C$4="",$C$4=0,B8=""),"",B8/$C$4) | D8: Total de ingressos/produtos | E8: =L_DIST_PROPON | F8: máximo | G8: =IF(C8="","",IF(C8>E8,"🔴 ACIMA DO LIMITE",IF(C8>=E8*MARGEM,"🟡 VERIFICAR","🟢 DENTRO DO LIMITE"))) | H8: Até o limite; use em ações de divulgação.
A9: Gratuita com caráter social/educativo | C9: =IF(OR($C$4="",$C$4=0,B9=""),"",B9/$C$4) | D9: Total de ingressos/produtos | E9: =L_DIST_SOCIAL | F9: mínimo | G9: =IF(C9="","🟡 VERIFICAR — informe a quantidade",IF(C9<E9,"🔴 ABAIXO DO MÍNIMO","🟢 DENTRO DO LIMITE")) | H9: Diga PARA QUEM (escolas, ONGs, comunidade) no Salic.
A10: Comercialização a preço popular | C10: =IF(OR($C$4="",$C$4=0,B10=""),"",B10/$C$4) | D10: Total de ingressos/produtos | E10: =L_DIST_POPULAR | F10: mínimo | G10: =IF(C10="","🟡 VERIFICAR — informe a quantidade",IF(AND(SUM($B$10:$B$11)=0,$B$9=$C$4),"🟡 VERIFICAR — projeto 100% gratuito: confirme como declarar no Salic",IF(C10<E10,"🔴 ABAIXO DO MÍNIMO","🟢 DENTRO DO LIMITE"))) | H10: Preço unitário não pode passar do teto de preço popular.
A11: Demais (comercialização ou outras gratuidades) | C11: =IF(OR($C$4="",$C$4=0,B11=""),"",B11/$C$4) | D11: Total de ingressos/produtos | F11: — | H11: Restante. Confira o preço médio abaixo.
A12: Soma das faixas | B12: =SUM(B7:B11) | C12: =IF(OR(C4="",C4=0),"",IF(B12=C4,"🟢 Soma confere com o total","🔴 Soma das faixas ≠ total informado"))
A14: Preço do ingresso popular (R$) | C14: =IF(B14="","",IF(B14>L_PRECO_POPULAR,"🔴 Acima do teto de preço popular","🟢 DENTRO DO LIMITE"))
A15: Receita total prevista com vendas (R$)
A16: Quantidade total comercializada
A17: Preço médio (R$) | B17: =IF(OR(B16="",B16=0),"",B15/B16) | C17: =IF(B17="","",IF(B17>L_TICKET_MEDIO,"🔴 Preço médio acima do teto configurado (confira a IN)","🟢 DENTRO DO LIMITE"))
A19: Medida adicional de ampliação de acesso prevista? (descreva)
A20: Ações formativas / de acesso vinculadas (descreva)

Sheet RADAR DE LIMITES
A1: PLANILHA 4 — RADAR DE LIMITES (CALCULADORAS A–H)
A2: Cada linha usa a BASE DE CÁLCULO prevista na IN 29/2026: remuneração do proponente e fornecedor → VALOR CAPTADO; administração, divulgação, acessibilidade e captação → VALOR DO PROJETO. Resultado é conferência prévia; o Salic e a análise do MinC prevalecem.
A4: ENTRADAS | B4: VALOR | D4: COMO PREENCHER
A5: Tipo de proponente | D5: Escolha: Pessoa física / MEI / Demais pessoa jurídica
A6: A remuneração se enquadra em exceção? (grupo artístico familiar, corpo artístico estável, grupo/coletivo que atua na execução) | B6: Não | D6: Se Sim, a planilha marca 🟡 VERIFICAR: confirme o enquadramento no texto oficial.
A7: VALOR DO PROJETO (calculado: soma das linhas 'Incentivo') | B7: =VALOR_INCENTIVO | D7: Soma automática do orçamento com fonte Incentivo fiscal.
A8: VALOR DO PROJETO exibido no Salic (opcional — sobrescreve) | D8: Se o Salic mostrar valor diferente (ex.: após cálculo dos custos vinculados), digite aqui.
A9: VALOR DO PROJETO usado nas contas | B9: =IF(AND(B8<>"",B8>0),B8,B7) | D9: Base para administração, divulgação, acessibilidade e captação.
A10: VALOR TOTAL DO PROJETO (todas as fontes) | B10: =VALOR_TOTAL | D10: Incentivo + outras fontes. Não é base dos limites percentuais do kit.
A11: Cenário de captação (% do valor do projeto que você espera captar) | B11: 1 | D11: Teste 100%, 75% e 50%. Remuneração e fornecedor são medidos sobre o que for CAPTADO.
A12: VALOR CAPTADO (cenário) | B12: =B9*B11 | D12: Base para remuneração do proponente e limite por fornecedor.
A13: É o seu PRIMEIRO projeto apresentado ao Pronac? | D13: Sim / Não
A14: Nº de projetos ativos que você já tem (sem contar este) | B14: 0 | D14: Consulte seus projetos no Salic.
A15: Soma dos valores dos projetos ativos (sem contar este) | B15: 0 | D15: Para conferir o teto global.
A16: Nº estimado de beneficiários / público total | D16: Para a calculadora H (valor por beneficiário).
A19: CALCULADORA | B19: VALOR INFORMADO | C19: BASE DE CÁLCULO | D19: BASE (R$) | E19: LIMITE APLICÁVEL | F19: PERCENTUAL RESULTANTE | G19: STATUS | H19: OBSERVAÇÃO
A20: A. Remuneração do proponente (inclui cônjuge/companheiro, coligada, sócio em comum) | B20: =SUMIFS('ORÇAMENTO'!$G$8:$G$207,'ORÇAMENTO'!$K$8:$K$207,"Remuneração do proponente",'ORÇAMENTO'!$H$8:$H$207,"Incentivo*")+SUMIFS('ORÇAMENTO'!$G$8:$G$207,'ORÇAMENTO'!$L$8:$L$207,"Sim",'ORÇAMENTO'!$K$8:$K$207,"<>Remuneração do proponente",'ORÇAMENTO'!$H$8:$H$207,"Incentivo*") | C20: VALOR CAPTADO | D20: =VALOR_CAPTADO | E20: =IF(OR(TIPO_PROP="Pessoa física",TIPO_PROP="MEI"),L_REM_PFMEI,L_REM_GERAL) | F20: =IF(OR(D20="",D20=0),"",B20/D20) | G20: =IF(F20="","",IF('RADAR DE LIMITES'!$B$6="Sim","🟡 VERIFICAR — exceção declarada: confirme o enquadramento",IF(TIPO_PROP="","🟡 VERIFICAR — informe o tipo de proponente",IF(OR(F20="",E20=""),"",IF(F20>E20,"🔴 ACIMA DO LIMITE",IF(F20>=E20*MARGEM,"🟡 VERIFICAR","🟢 DENTRO DO LIMITE")))))) | H20: Proponente só recebe se PRESTAR serviço previsto no orçamento analítico. Se captar menos, o limite em R$ diminui.
A21: B. Maior fornecedor (mesmo fornecedor, soma de todas as linhas) | B21: =IFERROR(MAX('ORÇAMENTO'!$P$8:$P$207)*VALOR_CAPTADO,0) | C21: VALOR CAPTADO | D21: =VALOR_CAPTADO | E21: =L_FORNECEDOR | F21: =IF(OR(D21="",D21=0),"",B21/D21) | G21: =IF(OR(F21="",E21=""),"",IF(F21>E21,"🔴 ACIMA DO LIMITE",IF(F21>=E21*MARGEM,"🟡 VERIFICAR","🟢 DENTRO DO LIMITE"))) | H21: Veja a coluna P do ORÇAMENTO para saber qual fornecedor. Há exceções na IN (ex.: restauro de bens culturais).
A22: C. Custos de administração | B22: =SUMIFS('ORÇAMENTO'!$G$8:$G$207,'ORÇAMENTO'!$K$8:$K$207,"Custos de administração",'ORÇAMENTO'!$H$8:$H$207,"Incentivo*") | C22: VALOR DO PROJETO | D22: =VALOR_PROJETO | E22: =L_ADM | F22: =IF(OR(D22="",D22=0),"",B22/D22) | G22: =IF(OR(F22="",E22=""),"",IF(F22>E22,"🔴 ACIMA DO LIMITE",IF(F22>=E22*MARGEM,"🟡 VERIFICAR","🟢 DENTRO DO LIMITE"))) | H22: Contador, tarifas, material de escritório do projeto etc. Não disfarce despesa de produção como administração (nem o contrário).
A23: D1. Acessibilidade, comunicação e divulgação acessíveis | B23: =SUMIFS('ORÇAMENTO'!$G$8:$G$207,'ORÇAMENTO'!$K$8:$K$207,"Acessibilidade / comunicação e divulgação acessíveis",'ORÇAMENTO'!$H$8:$H$207,"Incentivo*") | C23: VALOR DO PROJETO | D23: =VALOR_PROJETO | E23: =L_ACESS | F23: =IF(OR(D23="",D23=0),"",B23/D23) | G23: =IF(B23=0,"🔴 SEM CUSTO DE ACESSIBILIDADE — confira se as medidas estão previstas",IF(OR(F23="",E23=""),"",IF(F23>E23,"🔴 ACIMA DO LIMITE",IF(F23>=E23*MARGEM,"🟡 VERIFICAR","🟢 DENTRO DO LIMITE")))) | H23: Limite é TETO, não meta. Acessibilidade é obrigatória: 0% aqui é sinal de alerta (ver status).
A24: D2. Divulgação / comunicação | B24: =SUMIFS('ORÇAMENTO'!$G$8:$G$207,'ORÇAMENTO'!$K$8:$K$207,"Divulgação / comunicação",'ORÇAMENTO'!$H$8:$H$207,"Incentivo*") | C24: VALOR DO PROJETO | D24: =VALOR_PROJETO | E24: =L_DIVULG | F24: =IF(OR(D24="",D24=0),"",B24/D24) | G24: =IF(OR(F24="",E24=""),"",IF(F24>E24,"🔴 ACIMA DO LIMITE",IF(F24>=E24*MARGEM,"🟡 VERIFICAR","🟢 DENTRO DO LIMITE"))) | H24: Assessoria de comunicação, peças, impulsionamento. Precisa ter relação com o público do projeto.
A25: E. Remuneração de captação | B25: =SUMIFS('ORÇAMENTO'!$G$8:$G$207,'ORÇAMENTO'!$K$8:$K$207,"Remuneração de captação",'ORÇAMENTO'!$H$8:$H$207,"Incentivo*") | C25: VALOR DO PROJETO | D25: =VALOR_PROJETO | E25: =MIN(L_CAPT_PCT*VALOR_PROJETO,L_CAPT_TETO) | F25: =IF(OR(D25="",D25=0),"",B25/D25) | G25: =IF(B25=0,"🟢 DENTRO DO LIMITE (sem captador)",IF(B25>E25,"🔴 ACIMA DO LIMITE",IF(B25>=E25*MARGEM,"🟡 VERIFICAR","🟢 DENTRO DO LIMITE"))) | H25: Limite = MENOR entre 10% do valor do projeto e R$ 150.000. Pago proporcionalmente ao captado. Serviço ao proponente, nunca ao incentivador.
A26: F. Distribuição / democratização (detalhe na aba DISTRIBUICAO) | C26: Total de ingressos/produtos | G26: =IF(COUNTIF(DISTRIBUICAO!G7:G10,"🔴*")>0,"🔴 ACIMA/ABAIXO DO LIMITE — veja a aba",IF(COUNTIF(DISTRIBUICAO!G7:G10,"🟡*")>0,"🟡 VERIFICAR — veja a aba","🟢 DENTRO DO LIMITE")) | H26: Faixas máximas (promocionais) e mínimas (social/educativa e preço popular).
A27: H. Valor por beneficiário | B27: =VALOR_TOTAL | C27: Nº de beneficiários (B16) | D27: =B16 | E27: sem limite normativo | F27: =IF(OR(B16="",B16=0),"",VALOR_TOTAL/B16) | G27: =IF(F27="","🟡 VERIFICAR — informe beneficiários","🟢 Calculado — avalie se é razoável e explique na justificativa") | H27: Não há teto na IN para este indicador. Serve para você testar a coerência: custo alto por pessoa precisa de justificativa (ex.: formação intensiva, produto permanente).
A28: I. Primeiro projeto: dispensa de comprovar atuação cultural | B28: =MAX(VALOR_PROJETO,VALOR_TOTAL) | C28: Valor do projeto (o kit usa o MAIOR entre valor do projeto e valor total, por prudência) | E28: =L_INICIANTE | G28: =IF(B13="","🟡 VERIFICAR — responda se é o primeiro projeto",IF(B13="Não","🟡 Não se aplica: comprove atuação (portfólio no Salic)",IF(B28<=E28,"🟢 Pode estar dispensado de comprovar atuação — confira a redação oficial","🔴 Acima do limite: precisa comprovar atuação cultural"))) | H28: A dispensa é SÓ da comprovação de atuação na área cultural. Todos os outros requisitos e documentos continuam valendo.
A29: J. Limite de projetos ativos e teto global do proponente | B29: =B15+VALOR_PROJETO | C29: Soma dos projetos ativos + este | D29: =IF(TIPO_PROP="Pessoa física",L_PF_QTD,IF(TIPO_PROP="MEI",L_MEI_QTD,IF(TIPO_PROP="","",L_PJ_QTD))) | E29: =IF(TIPO_PROP="Pessoa física",L_PF_TETO,IF(TIPO_PROP="MEI",L_MEI_TETO,IF(TIPO_PROP="","",L_PJ_TETO))) | F29: =IF(OR(E29="",E29=0),"",B29/E29) | G29: =IF(TIPO_PROP="","🟡 VERIFICAR — informe o tipo de proponente",IF(OR(B14+1>D29,B29>E29),"🔴 ACIMA DO LIMITE",IF(B29>=E29*MARGEM,"🟡 VERIFICAR","🟢 DENTRO DO LIMITE"))) | H29: Coluna D mostra a QUANTIDADE máxima de projetos ativos; coluna E o teto global em R$.
A31: G. PERCENTUAL DE CADA CATEGORIA (sobre o VALOR DO PROJETO)
A32: Categoria | B32: Valor (incentivo) | C32: % do valor do projeto | D32: Limite (se houver)
A33: Produção / atividade-fim | B33: =SUMIFS('ORÇAMENTO'!$G$8:$G$207,'ORÇAMENTO'!$K$8:$K$207,"Produção / atividade-fim",'ORÇAMENTO'!$H$8:$H$207,"Incentivo*") | C33: =IF(VALOR_PROJETO=0,"",B33/VALOR_PROJETO) | D33: —
A34: Cachê – artista solo | B34: =SUMIFS('ORÇAMENTO'!$G$8:$G$207,'ORÇAMENTO'!$K$8:$K$207,"Cachê – artista solo",'ORÇAMENTO'!$H$8:$H$207,"Incentivo*") | C34: =IF(VALOR_PROJETO=0,"",B34/VALOR_PROJETO) | D34: por apresentação (ver PARAMETROS)
A35: Cachê – grupo ou coletivo | B35: =SUMIFS('ORÇAMENTO'!$G$8:$G$207,'ORÇAMENTO'!$K$8:$K$207,"Cachê – grupo ou coletivo",'ORÇAMENTO'!$H$8:$H$207,"Incentivo*") | C35: =IF(VALOR_PROJETO=0,"",B35/VALOR_PROJETO) | D35: por apresentação (ver PARAMETROS)
A36: Cachê – músico de orquestra | B36: =SUMIFS('ORÇAMENTO'!$G$8:$G$207,'ORÇAMENTO'!$K$8:$K$207,"Cachê – músico de orquestra",'ORÇAMENTO'!$H$8:$H$207,"Incentivo*") | C36: =IF(VALOR_PROJETO=0,"",B36/VALOR_PROJETO) | D36: por apresentação (ver PARAMETROS)
A37: Cachê – maestro / regente | B37: =SUMIFS('ORÇAMENTO'!$G$8:$G$207,'ORÇAMENTO'!$K$8:$K$207,"Cachê – maestro / regente",'ORÇAMENTO'!$H$8:$H$207,"Incentivo*") | C37: =IF(VALOR_PROJETO=0,"",B37/VALOR_PROJETO) | D37: por apresentação (ver PARAMETROS)
A38: Cachê – palestrante / conferencista | B38: =SUMIFS('ORÇAMENTO'!$G$8:$G$207,'ORÇAMENTO'!$K$8:$K$207,"Cachê – palestrante / conferencista",'ORÇAMENTO'!$H$8:$H$207,"Incentivo*") | C38: =IF(VALOR_PROJETO=0,"",B38/VALOR_PROJETO) | D38: por apresentação (ver PARAMETROS)
A39: Remuneração do proponente | B39: =SUMIFS('ORÇAMENTO'!$G$8:$G$207,'ORÇAMENTO'!$K$8:$K$207,"Remuneração do proponente",'ORÇAMENTO'!$H$8:$H$207,"Incentivo*") | C39: =IF(VALOR_PROJETO=0,"",B39/VALOR_PROJETO) | D39: sobre VALOR CAPTADO (ver A)
A40: Custos de administração | B40: =SUMIFS('ORÇAMENTO'!$G$8:$G$207,'ORÇAMENTO'!$K$8:$K$207,"Custos de administração",'ORÇAMENTO'!$H$8:$H$207,"Incentivo*") | C40: =IF(VALOR_PROJETO=0,"",B40/VALOR_PROJETO) | D40: =L_ADM
A41: Divulgação / comunicação | B41: =SUMIFS('ORÇAMENTO'!$G$8:$G$207,'ORÇAMENTO'!$K$8:$K$207,"Divulgação / comunicação",'ORÇAMENTO'!$H$8:$H$207,"Incentivo*") | C41: =IF(VALOR_PROJETO=0,"",B41/VALOR_PROJETO) | D41: =L_DIVULG
A42: Acessibilidade / comunicação e divulgação acessíveis | B42: =SUMIFS('ORÇAMENTO'!$G$8:$G$207,'ORÇAMENTO'!$K$8:$K$207,"Acessibilidade / comunicação e divulgação acessíveis",'ORÇAMENTO'!$H$8:$H$207,"Incentivo*") | C42: =IF(VALOR_PROJETO=0,"",B42/VALOR_PROJETO) | D42: =L_ACESS
A43: Remuneração de captação | B43: =SUMIFS('ORÇAMENTO'!$G$8:$G$207,'ORÇAMENTO'!$K$8:$K$207,"Remuneração de captação",'ORÇAMENTO'!$H$8:$H$207,"Incentivo*") | C43: =IF(VALOR_PROJETO=0,"",B43/VALOR_PROJETO) | D43: 10% / R$150 mil (ver E)
A44: Tributos e encargos | B44: =SUMIFS('ORÇAMENTO'!$G$8:$G$207,'ORÇAMENTO'!$K$8:$K$207,"Tributos e encargos",'ORÇAMENTO'!$H$8:$H$207,"Incentivo*") | C44: =IF(VALOR_PROJETO=0,"",B44/VALOR_PROJETO) | D44: —
A45: Outros (explique na observação) | B45: =SUMIFS('ORÇAMENTO'!$G$8:$G$207,'ORÇAMENTO'!$K$8:$K$207,"Outros (explique na observação)",'ORÇAMENTO'!$H$8:$H$207,"Incentivo*") | C45: =IF(VALOR_PROJETO=0,"",B45/VALOR_PROJETO) | D45: —
A46: TOTAL | B46: =SUM(B33:B45) | C46: =IF(VALOR_PROJETO=0,"",B46/VALOR_PROJETO)
A47: Linhas do orçamento sem categoria (incentivo) | B47: =SUMIFS('ORÇAMENTO'!$G$8:$G$207,'ORÇAMENTO'!$K$8:$K$207,"",'ORÇAMENTO'!$H$8:$H$207,"Incentivo*") | C47: =IF(B47>0,"🟡 Classifique todas as linhas","🟢 Tudo classificado")
A49: E SE EU CAPTAR MENOS? — remuneração do proponente por cenário
A50: Cenário de captação | B50: Valor captado | C50: Limite de remuneração em R$ | D50: Remuneração prevista | E50: % sobre o captado | F50: Status
A51: 1 | B51: =VALOR_PROJETO*A51 | C51: =B51*$E$20 | D51: =$B$20 | E51: =IF(B51=0,"",D51/B51) | F51: =IF(E51="","",IF(E51>$E$20,"🔴 Reduza a remuneração neste cenário","🟢 OK"))
A52: 0.75 | B52: =VALOR_PROJETO*A52 | C52: =B52*$E$20 | D52: =$B$20 | E52: =IF(B52=0,"",D52/B52) | F52: =IF(E52="","",IF(E52>$E$20,"🔴 Reduza a remuneração neste cenário","🟢 OK"))
A53: 0.5 | B53: =VALOR_PROJETO*A53 | C53: =B53*$E$20 | D53: =$B$20 | E53: =IF(B53=0,"",D53/B53) | F53: =IF(E53="","",IF(E53>$E$20,"🔴 Reduza a remuneração neste cenário","🟢 OK"))
A54: 0.25 | B54: =VALOR_PROJETO*A54 | C54: =B54*$E$20 | D54: =$B$20 | E54: =IF(B54=0,"",D54/B54) | F54: =IF(E54="","",IF(E54>$E$20,"🔴 Reduza a remuneração neste cenário","🟢 OK"))
A55: Leitura: a remuneração do proponente é limitada pelo VALOR CAPTADO. Se o projeto captar só parte do valor, o valor em reais que você pode receber cai junto. Planeje a execução parcial desde já.

Sheet MATRIZ CONSISTENCIA
A1: PLANILHA 7 — MATRIZ DE CONSISTÊNCIA
A2: Parte 1: cada objetivo específico precisa virar meta → produto → despesa → atividade → público. Copie o NOME EXATO do item do orçamento e da atividade do cronograma: a planilha confere se eles existem.
A4: Objetivo específico | B4: Meta (com número) | C4: Produto | D4: Item do ORÇAMENTO (nome exato) | E4: Atividade do CRONOGRAMA (nome exato) | F4: Público / faixa do plano de distribuição | G4: Item existe no orçamento? | H4: Atividade existe no cronograma? | I4: Revisão manual | J4: RESULTADO
G5: =IF(D5="","",IF(COUNTIF('ORÇAMENTO'!$B$8:$B$207,D5)>0,"Sim","Não")) | H5: =IF(E5="","",IF(COUNTIF(CRONOGRAMA!$A$8:$A$67,E5)>0,"Sim","Não")) | J5: =IF(A5="","",IF(OR(COUNTBLANK(B5:F5)>2,G5="Não",H5="Não"),"🔴 INCONSISTENTE",IF(OR(COUNTBLANK(B5:F5)>0,I5="Revisar"),"🟡 REVISAR","🟢 COERENTE")))
G6: =IF(D6="","",IF(COUNTIF('ORÇAMENTO'!$B$8:$B$207,D6)>0,"Sim","Não")) | H6: =IF(E6="","",IF(COUNTIF(CRONOGRAMA!$A$8:$A$67,E6)>0,"Sim","Não")) | J6: =IF(A6="","",IF(OR(COUNTBLANK(B6:F6)>2,G6="Não",H6="Não"),"🔴 INCONSISTENTE",IF(OR(COUNTBLANK(B6:F6)>0,I6="Revisar"),"🟡 REVISAR","🟢 COERENTE")))
G7: =IF(D7="","",IF(COUNTIF('ORÇAMENTO'!$B$8:$B$207,D7)>0,"Sim","Não")) | H7: =IF(E7="","",IF(COUNTIF(CRONOGRAMA!$A$8:$A$67,E7)>0,"Sim","Não")) | J7: =IF(A7="","",IF(OR(COUNTBLANK(B7:F7)>2,G7="Não",H7="Não"),"🔴 INCONSISTENTE",IF(OR(COUNTBLANK(B7:F7)>0,I7="Revisar"),"🟡 REVISAR","🟢 COERENTE")))
G8: =IF(D8="","",IF(COUNTIF('ORÇAMENTO'!$B$8:$B$207,D8)>0,"Sim","Não")) | H8: =IF(E8="","",IF(COUNTIF(CRONOGRAMA!$A$8:$A$67,E8)>0,"Sim","Não")) | J8: =IF(A8="","",IF(OR(COUNTBLANK(B8:F8)>2,G8="Não",H8="Não"),"🔴 INCONSISTENTE",IF(OR(COUNTBLANK(B8:F8)>0,I8="Revisar"),"🟡 REVISAR","🟢 COERENTE")))
G9: =IF(D9="","",IF(COUNTIF('ORÇAMENTO'!$B$8:$B$207,D9)>0,"Sim","Não")) | H9: =IF(E9="","",IF(COUNTIF(CRONOGRAMA!$A$8:$A$67,E9)>0,"Sim","Não")) | J9: =IF(A9="","",IF(OR(COUNTBLANK(B9:F9)>2,G9="Não",H9="Não"),"🔴 INCONSISTENTE",IF(OR(COUNTBLANK(B9:F9)>0,I9="Revisar"),"🟡 REVISAR","🟢 COERENTE")))
G10: =IF(D10="","",IF(COUNTIF('ORÇAMENTO'!$B$8:$B$207,D10)>0,"Sim","Não")) | H10: =IF(E10="","",IF(COUNTIF(CRONOGRAMA!$A$8:$A$67,E10)>0,"Sim","Não")) | J10: =IF(A10="","",IF(OR(COUNTBLANK(B10:F10)>2,G10="Não",H10="Não"),"🔴 INCONSISTENTE",IF(OR(COUNTBLANK(B10:F10)>0,I10="Revisar"),"🟡 REVISAR","🟢 COERENTE")))
G11: =IF(D11="","",IF(COUNTIF('ORÇAMENTO'!$B$8:$B$207,D11)>0,"Sim","Não")) | H11: =IF(E11="","",IF(COUNTIF(CRONOGRAMA!$A$8:$A$67,E11)>0,"Sim","Não")) | J11: =IF(A11="","",IF(OR(COUNTBLANK(B11:F11)>2,G11="Não",H11="Não"),"🔴 INCONSISTENTE",IF(OR(COUNTBLANK(B11:F11)>0,I11="Revisar"),"🟡 REVISAR","🟢 COERENTE")))
G12: =IF(D12="","",IF(COUNTIF('ORÇAMENTO'!$B$8:$B$207,D12)>0,"Sim","Não")) | H12: =IF(E12="","",IF(COUNTIF(CRONOGRAMA!$A$8:$A$67,E12)>0,"Sim","Não")) | J12: =IF(A12="","",IF(OR(COUNTBLANK(B12:F12)>2,G12="Não",H12="Não"),"🔴 INCONSISTENTE",IF(OR(COUNTBLANK(B12:F12)>0,I12="Revisar"),"🟡 REVISAR","🟢 COERENTE")))
G13: =IF(D13="","",IF(COUNTIF('ORÇAMENTO'!$B$8:$B$207,D13)>0,"Sim","Não")) | H13: =IF(E13="","",IF(COUNTIF(CRONOGRAMA!$A$8:$A$67,E13)>0,"Sim","Não")) | J13: =IF(A13="","",IF(OR(COUNTBLANK(B13:F13)>2,G13="Não",H13="Não"),"🔴 INCONSISTENTE",IF(OR(COUNTBLANK(B13:F13)>0,I13="Revisar"),"🟡 REVISAR","🟢 COERENTE")))
G14: =IF(D14="","",IF(COUNTIF('ORÇAMENTO'!$B$8:$B$207,D14)>0,"Sim","Não")) | H14: =IF(E14="","",IF(COUNTIF(CRONOGRAMA!$A$8:$A$67,E14)>0,"Sim","Não")) | J14: =IF(A14="","",IF(OR(COUNTBLANK(B14:F14)>2,G14="Não",H14="Não"),"🔴 INCONSISTENTE",IF(OR(COUNTBLANK(B14:F14)>0,I14="Revisar"),"🟡 REVISAR","🟢 COERENTE")))
G15: =IF(D15="","",IF(COUNTIF('ORÇAMENTO'!$B$8:$B$207,D15)>0,"Sim","Não")) | H15: =IF(E15="","",IF(COUNTIF(CRONOGRAMA!$A$8:$A$67,E15)>0,"Sim","Não")) | J15: =IF(A15="","",IF(OR(COUNTBLANK(B15:F15)>2,G15="Não",H15="Não"),"🔴 INCONSISTENTE",IF(OR(COUNTBLANK(B15:F15)>0,I15="Revisar"),"🟡 REVISAR","🟢 COERENTE")))
G16: =IF(D16="","",IF(COUNTIF('ORÇAMENTO'!$B$8:$B$207,D16)>0,"Sim","Não")) | H16: =IF(E16="","",IF(COUNTIF(CRONOGRAMA!$A$8:$A$67,E16)>0,"Sim","Não")) | J16: =IF(A16="","",IF(OR(COUNTBLANK(B16:F16)>2,G16="Não",H16="Não"),"🔴 INCONSISTENTE",IF(OR(COUNTBLANK(B16:F16)>0,I16="Revisar"),"🟡 REVISAR","🟢 COERENTE")))
... G19: =IF(D19="","",IF(COUNTIF('ORÇAMENTO'!$B$8:$B$207,D19)>0,"Sim","Não")) | H19: =IF(E19="","",IF(COUNTIF(CRONOGRAMA!$A$8:$A$67,E19)>0,"Sim","Não")) | J19: =IF(A19="","",IF(OR(COUNTBLANK(B19:F19)>2,G19="Não",H19="Não"),"🔴 INCONSISTENTE",IF(OR(COUNTBLANK(B19:F19)>0,I19="Revisar"),"🟡 REVISAR","🟢 COERENTE")))
A22: PARTE 2 — AS 6 PERGUNTAS DE CONSISTÊNCIA
A23: Verificação | B23: Pergunta de controle | C23: Resposta (Sim / Parcial / Não) | D23: RESULTADO | E23: Onde corrigir
A24: Objetivo x Meta | B24: Todo objetivo específico tem pelo menos uma meta com número? | D24: =IF(C24="","",IF(C24="Sim","🟢 COERENTE",IF(C24="Parcial","🟡 REVISAR","🔴 INCONSISTENTE"))) | E24: MAPA DO PROJETO (objetivos/metas)
A25: Meta x Produto | B25: Toda meta corresponde a um produto cadastrado no plano de distribuição? | D25: =IF(C25="","",IF(C25="Sim","🟢 COERENTE",IF(C25="Parcial","🟡 REVISAR","🔴 INCONSISTENTE"))) | E25: Salic – Plano de distribuição
A26: Produto x Orçamento | B26: Todo produto tem as despesas necessárias para existir (e nenhuma despesa sobra)? | D26: =IF(C26="","",IF(C26="Sim","🟢 COERENTE",IF(C26="Parcial","🟡 REVISAR","🔴 INCONSISTENTE"))) | E26: ORÇAMENTO
A27: Atividade x Cronograma | B27: Toda atividade da metodologia aparece no cronograma com data e responsável? | D27: =IF(C27="","",IF(C27="Sim","🟢 COERENTE",IF(C27="Parcial","🟡 REVISAR","🔴 INCONSISTENTE"))) | E27: CRONOGRAMA
A28: Público x Distribuição | B28: O público descrito bate com as faixas de distribuição (gratuidade, preço popular, locais)? | D28: =IF(C28="","",IF(C28="Sim","🟢 COERENTE",IF(C28="Parcial","🟡 REVISAR","🔴 INCONSISTENTE"))) | E28: DISTRIBUICAO / Salic
A29: Despesa x Metodologia | B29: Toda despesa tem 'por que existe' preenchido e ligado a uma etapa da metodologia? | D29: =IF(C29="","",IF(C29="Sim","🟢 COERENTE",IF(C29="Parcial","🟡 REVISAR","🔴 INCONSISTENTE"))) | E29: ORÇAMENTO coluna M
A31: Checagem automática | B31: Despesas sem 'por que existe' no ORÇAMENTO: | D31: =COUNTIFS('ORÇAMENTO'!$G$8:$G$207,">0",'ORÇAMENTO'!$M$8:$M$207,"")
B32: Atividades do cronograma em etapa sem despesa: | D32: =COUNTIF(CRONOGRAMA!$H$8:$H$67,"*Etapa sem despesa*")

Sheet CHECKLIST SALIC
A1: PLANILHA 5 — CHECKLIST SALIC (DO LOGIN AO ENVIO)
A2: Use enquanto preenche o sistema. Os nomes das telas podem mudar: siga sempre o Manual do Proponente vigente (IN 2026) publicado pelo MinC.
A4: Passo | B4: Item | C4: Obrigatório? | D4: Preparado? | E4: Revisado? | F4: Observação
A5: 1 Acesso | B5: Conta gov.br ativa, com senha e nível de acesso exigido pelo sistema | C5: Sim
A6: 1 Acesso | B6: Acesso ao Salic realizado com o CPF do responsável | C6: Sim
A7: 2 Cadastro | B7: Cadastro do proponente (PF ou PJ) completo e atualizado | C7: Sim
A8: 2 Cadastro | B8: Dados de contato (e-mail e telefone) que você realmente acompanha | C8: Sim
A9: 2 Cadastro | B9: Vinculação do responsável/procurador ao proponente PJ, quando aplicável | C9: Depende
A10: 2 Cadastro | B10: Portfólio/comprovação de atuação cultural cadastrado no Salic (ou confirmação da dispensa de iniciante) | C10: Depende
A11: 3 Nova proposta | B11: Declaração de responsabilidade lida antes de aceitar | C11: Sim
A12: 4 Identificação | B12: Nome do projeto, área/segmento e enquadramento conferidos | C12: Sim
A13: 4 Identificação | B13: Tipicidade/limites de orçamento conferidos na tela de identificação | C13: Sim
A14: 5 Resumo | B14: Resumo colado do MAPA DO PROJETO e revisado | C14: Sim
A15: 6 Objetivos | B15: Objetivo geral e específicos coerentes com metas | C15: Sim
A16: 7 Justificativa | B16: Justificativa específica (sem texto genérico) | C16: Sim
... A31: 17 Envio | B31: Acompanhamento de diligências no Salic e no e-mail cadastrado | C31: Sim
B33: Itens preparados | D33: =COUNTIF(D5:D31,"Sim")&" / "&(COUNTA(B5:B31)-COUNTIF(D5:D31,"N/A"))
B34: Itens revisados | D34: =COUNTIF(E5:E31,"Sim")&" / "&(COUNTA(B5:B31)-COUNTIF(E5:E31,"N/A"))

Sheet CHECKLIST DOCUMENTOS
A1: PLANILHA 6 — CHECKLIST DE DOCUMENTOS
A2: A lista oficial está no Manual do Proponente e na IN 29/2026 (e anexos). Esta planilha organiza; ela não substitui a lista oficial. 2026: documentos obrigatórios devem ser anexados na apresentação.
A4: Grupo | B4: Documento | C4: Obrigatório? | D4: Aplicável ao meu projeto? | E4: Já tenho? | F4: Validade | G4: Observação
A5: PROPONENTE | B5: Cadastro completo do proponente no Salic (dados pessoais ou da PJ) | C5: Sim | G5: Base para tudo.
A6: PROPONENTE | B6: Documento de identificação / CPF do proponente PF ou do responsável legal | C6: Conforme Manual | G6: Confira o que o Salic pede no cadastro.
A7: PROPONENTE | B7: CNPJ, ato constitutivo/estatuto/contrato social e ata de eleição da diretoria (PJ) | C7: Sim para PJ | G7: Natureza cultural deve constar no ato constitutivo/CNAE (PJ).
A8: PROPONENTE | B8: Comprovação de atuação na área cultural (portfólio no Salic) | C8: Depende | G8: Dispensa para primeiro projeto até R$ 200 mil — confira a redação oficial.
A9: PROPONENTE | B9: Procuração, quando outra pessoa opera o Salic em nome do proponente | C9: Eventual | G9: Somente se houver procurador.
A10: PROPONENTE | B10: Situação de regularidade (certidões) exigidas nas fases previstas | C10: Conforme fase | G10: Algumas exigências ocorrem em fases posteriores; confira.
A11: PROJETO | B11: Currículo/portfólio dos principais profissionais do projeto | C11: Conforme Manual | G11: Mostra capacidade de execução.
A12: PROJETO | B12: Cartas de anuência/aceite dos principais participantes | C12: Conforme segmento | G12: Artistas, curadores, instituições parceiras.
A13: PROJETO | B13: Anuência/autorização do local de realização | C13: Conforme segmento | G13: Quando o local é de terceiros.
A14: ESPECÍFICOS | B14: Documentos exigidos para o segmento (ex.: patrimônio, audiovisual, livro, plano anual) | C14: Depende do segmento | G14: Veja o anexo/lista do segmento na norma e no Manual.
A15: ESPECÍFICOS | B15: Autorização de órgãos de patrimônio (tombamento) — projetos de patrimônio | C15: Depende | G15: Iphan/órgão estadual/municipal quando aplicável.
A16: ESPECÍFICOS | B16: Autorização de direitos autorais / cessão de direitos, quando aplicável | C16: Depende | G16: Obras de terceiros.
... A19: EVENTUAIS | B19: Documentos solicitados em diligência | C19: Eventual | G19: Responda dentro do prazo indicado.
B28: Documentos aplicáveis ainda pendentes | C28: =COUNTIFS(D5:D26,"Sim",E5:E26,"<>Sim")
B29: Documentos vencendo em até 30 dias | C29: =COUNTIFS(F5:F26,">="&TODAY(),F5:F26,"<="&TODAY()+30)

Sheet CHECKLIST FINAL
A1: CHECKLIST FINAL — ANTES DE CLICAR EM ENVIAR
A2: Marque SIM, NÃO ou N/A. Meta: zero NÃO. Qualquer NÃO = corrija antes de enviar.
A4: Bloco | B4: Verificação | C4: SIM / NÃO / N/A | D4: Onde corrigir
A5: A. PROPONENTE | B5: Meu cadastro no Salic está completo, com e-mail e telefone que eu acompanho. | D5: Salic – cadastro
A6: A. PROPONENTE | B6: Sei se sou PF, MEI ou demais PJ e conferi o limite de projetos ativos e o teto global do meu tipo. | D6: RADAR – linha J
A7: A. PROPONENTE | B7: Se sou PJ, a finalidade cultural consta do ato constitutivo / atividade econômica. | D7: Documentos da PJ
A8: A. PROPONENTE | B8: Comprovação de atuação cultural cadastrada (portfólio) OU confirmei que estou na dispensa de primeiro projeto até R$ 200 mil. | D8: RADAR – linha I
A9: A. PROPONENTE | B9: Se alguém opera o Salic por mim, a procuração/vinculação está correta. | D9: Salic – cadastro
A10: B. PROJETO | B10: Nome do projeto claro e igual em todos os documentos. | D10: MAPA DO PROJETO
A11: B. PROJETO | B11: Área, segmento e enquadramento conferidos na tela de identificação. | D11: Salic – identificação
A12: B. PROJETO | B12: Resumo responde O QUÊ, ONDE, QUANDO, PARA QUEM e COMO. | D12: MAPA DO PROJETO
A13: B. PROJETO | B13: Período de execução dentro do limite de execução da IN 29/2026 (máx. 36 meses). | D13: CRONOGRAMA
A14: C. OBJETIVOS | B14: O objetivo geral é uma frase, com verbo no infinitivo. | D14: MAPA DO PROJETO
A15: C. OBJETIVOS | B15: Cada objetivo específico tem pelo menos uma meta com número. | D15: MATRIZ – Objetivo x Meta
A16: C. OBJETIVOS | B16: Cada meta corresponde a um produto do plano de distribuição. | D16: MATRIZ – Meta x Produto
... A58: N. REVISÃO FINAL | B58: Lista de pendências do Salic está zerada e salvei comprovante do envio. | D58: Salic
B60: SIM | C60: =COUNTIF(C5:C58,"SIM")
B61: NÃO | C61: =COUNTIF(C5:C58,"NÃO")
B62: N/A | C62: =COUNTIF(C5:C58,"N/A")
B63: Em branco | C63: =COUNTBLANK(C5:C58)
B64: RESULTADO | C64: =IF(C61>0,"🔴 NÃO ENVIE AINDA: "&C61&" item(ns) NÃO",IF(C63>0,"🟡 Faltam "&C63&" itens","🟢 Pronto para revisão final e envio"))

Sheet CONTROLE NORMATIVO
A1: ÚLTIMA VERIFICAÇÃO NORMATIVA
A2: Registre cada vez que você conferir a norma oficial. Se algo mudou, atualize a aba PARAMETROS.
A4: Data | B4: Norma consultada | C4: Versão | D4: Alterações relevantes | E4: Link oficial
A5: 46290 | B5: Instrução Normativa MinC nº 29/2026 | C5: 29/01/2026 (DOU 30/01/2026) | D5: Base deste kit. Revogou a IN MinC nº 23/2025. Novos limites por proponente, prazo máx. de execução de 36 meses, documentos obrigatórios na apresentação, acessibilidade reforçada. | E5: https://www.gov.br/cultura/pt-br/acesso-a-informacao/legislacao-e-normativas/instrucao-normativa-minc-no-29-de-29-de-janeiro-de-2026
A6: 46290 | B6: Lei nº 8.313/1991 (Lei Rouanet) | C6: compilada | D6: Base legal do Pronac e do incentivo fiscal. | E6: https://www.planalto.gov.br/ccivil_03/leis/l8313cons.htm
A7: 46290 | B7: Decreto nº 11.453/2023 | C7: vigente | D7: Regulamenta os mecanismos de fomento do Pronac. | E7: https://www.planalto.gov.br/ccivil_03/_ato2023-2026/2023/decreto/d11453.htm
A8: 46290 | B8: Manual do Proponente – IN 2026 | C8: publicado pelo MinC | D8: Passo a passo no Salic. | E8: https://www.gov.br/cultura/pt-br/centrais-de-conteudo/marcas-e-logotipos/marcas-rouanet/ManualdoProponenteIN2026DEFINITIVO2.pdf
